{"data":{"0":null,"symbol":["XAS","XAS","XAS","XAS","XAS","XAS","XAS","XAS","XAS"],"history":{"2":{"position":177,"name":"Asch","symbol":"XAS","identifier":"asch","category":"currency","marketCap":{"usd":41109113,"btc":0,"eur":0,"cny":0,"gbp":0,"cad":0,"rub":0,"hkd":0,"jpy":0,"aud":0},"price":{"usd":0.440351,"btc":0,"eur":0,"cny":0,"cad":0,"rub":0,"hkd":0,"jpy":0,"aud":0},"availableSupply":93355331,"volume24":{"usd":3027860,"btc":0,"eur":0,"cny":0,"gbp":0,"cad":0,"rub":0,"hkd":0,"jpy":0,"aud":0},"change1h":0.19,"change24h":0.3,"change7d":2.04,"timestamp":1532318403,"date":"23-07-2018"},"3":{"position":176,"name":"Asch","symbol":"XAS","identifier":"asch","category":"currency","marketCap":{"usd":41368735,"btc":0,"eur":0,"cny":0,"gbp":0,"cad":0,"rub":0,"hkd":0,"jpy":0,"aud":0},"price":{"usd":0.443132,"btc":0,"eur":0,"cny":0,"cad":0,"rub":0,"hkd":0,"jpy":0,"aud":0},"availableSupply":93355331,"volume24":{"usd":3096060,"btc":0,"eur":0,"cny":0,"gbp":0,"cad":0,"rub":0,"hkd":0,"jpy":0,"aud":0},"change1h":0.55,"change24h":0.87,"change7d":2.54,"timestamp":1532319902,"date":"23-07-2018"},"4":{"position":178,"name":"Asch","symbol":"XAS","identifier":"asch","category":"currency","marketCap":{"usd":41208163,"btc":0,"eur":0,"cny":0,"gbp":0,"cad":0,"rub":0,"hkd":0,"jpy":0,"aud":0},"price":{"usd":0.441412,"btc":0,"eur":0,"cny":0,"cad":0,"rub":0,"hkd":0,"jpy":0,"aud":0},"availableSupply":93355331,"volume24":{"usd":3122640,"btc":0,"eur":0,"cny":0,"gbp":0,"cad":0,"rub":0,"hkd":0,"jpy":0,"aud":0},"change1h":-0.11,"change24h":0.33,"change7d":1.97,"timestamp":1532321402,"date":"23-07-2018"},"5":{"position":178,"name":"Asch","symbol":"XAS","identifier":"asch","category":"currency","marketCap":{"usd":41208163,"btc":0,"eur":0,"cny":0,"gbp":0,"cad":0,"rub":0,"hkd":0,"jpy":0,"aud":0},"price":{"usd":0.441412,"btc":0,"eur":0,"cny":0,"cad":0,"rub":0,"hkd":0,"jpy":0,"aud":0},"availableSupply":93355331,"volume24":{"usd":3122640,"btc":0,"eur":0,"cny":0,"gbp":0,"cad":0,"rub":0,"hkd":0,"jpy":0,"aud":0},"change1h":-0.11,"change24h":0.33,"change7d":1.97,"timestamp":1532322002,"date":"23-07-2018"},"6":{"position":179,"name":"Asch","symbol":"XAS","identifier":"asch","category":"currency","marketCap":{"usd":40952837,"btc":0,"eur":0,"cny":0,"gbp":0,"cad":0,"rub":0,"hkd":0,"jpy":0,"aud":0},"price":{"usd":0.438677,"btc":0,"eur":0,"cny":0,"cad":0,"rub":0,"hkd":0,"jpy":0,"aud":0},"availableSupply":93355331,"volume24":{"usd":3132100,"btc":0,"eur":0,"cny":0,"gbp":0,"cad":0,"rub":0,"hkd":0,"jpy":0,"aud":0},"change1h":-0.41,"change24h":-0.27,"change7d":1.19,"timestamp":1532323502,"date":"23-07-2018"},"7":{"position":180,"name":"Asch","symbol":"XAS","identifier":"asch","category":"currency","marketCap":{"usd":40851639,"btc":0,"eur":0,"cny":0,"gbp":0,"cad":0,"rub":0,"hkd":0,"jpy":0,"aud":0},"price":{"usd":0.437593,"btc":0,"eur":0,"cny":0,"cad":0,"rub":0,"hkd":0,"jpy":0,"aud":0},"availableSupply":93355331,"volume24":{"usd":3158620,"btc":0,"eur":0,"cny":0,"gbp":0,"cad":0,"rub":0,"hkd":0,"jpy":0,"aud":0},"change1h":-0.71,"change24h":-0.16,"change7d":0.8,"timestamp":1532325002,"date":"23-07-2018"},"8":{"position":180,"name":"Asch","symbol":"XAS","identifier":"asch","category":"currency","marketCap":{"usd":40851639,"btc":0,"eur":0,"cny":0,"gbp":0,"cad":0,"rub":0,"hkd":0,"jpy":0,"aud":0},"price":{"usd":0.437593,"btc":0,"eur":0,"cny":0,"cad":0,"rub":0,"hkd":0,"jpy":0,"aud":0},"availableSupply":93355331,"volume24":{"usd":3158620,"btc":0,"eur":0,"cny":0,"gbp":0,"cad":0,"rub":0,"hkd":0,"jpy":0,"aud":0},"change1h":-0.71,"change24h":-0.16,"change7d":0.8,"timestamp":1532325602,"date":"23-07-2018"},"9":{"position":180,"name":"Asch","symbol":"XAS","identifier":"asch","category":"currency","marketCap":{"usd":40819805,"btc":0,"eur":0,"cny":0,"gbp":0,"cad":0,"rub":0,"hkd":0,"jpy":0,"aud":0},"price":{"usd":0.437252,"btc":0,"eur":0,"cny":0,"cad":0,"rub":0,"hkd":0,"jpy":0,"aud":0},"availableSupply":93355331,"volume24":{"usd":3182780,"btc":0,"eur":0,"cny":0,"gbp":0,"cad":0,"rub":0,"hkd":0,"jpy":0,"aud":0},"change1h":-0.57,"change24h":-0.28,"change7d":0.58,"timestamp":1532327105,"date":"23-07-2018"},"10":{"position":180,"name":"Asch","symbol":"XAS","identifier":"asch","category":"currency","marketCap":{"usd":41164940,"btc":0,"eur":0,"cny":0,"gbp":0,"cad":0,"rub":0,"hkd":0,"jpy":0,"aud":0},"price":{"usd":0.440949,"btc":0,"eur":0,"cny":0,"cad":0,"rub":0,"hkd":0,"jpy":0,"aud":0},"availableSupply":93355331,"volume24":{"usd":3246680,"btc":0,"eur":0,"cny":0,"gbp":0,"cad":0,"rub":0,"hkd":0,"jpy":0,"aud":0},"change1h":0.55,"change24h":0.58,"change7d":1.29,"timestamp":1532328601,"date":"23-07-2018"}},"s":{"price":{"gbp":[0,0,0,0,0,0,0,0,0]}}}}