{"data":{"0":null,"symbol":["XBTS","XBTS","XBTS","XBTS","XBTS","XBTS","XBTS","XBTS","XBTS"],"history":{"2":{"position":1272,"name":"Beatcoin","symbol":"XBTS","identifier":"beatcoin","category":"currency","marketCap":{"usd":94939,"btc":0,"eur":0,"cny":0,"gbp":0,"cad":0,"rub":0,"hkd":0,"jpy":0,"aud":0},"price":{"usd":0.0622676,"btc":0,"eur":0,"cny":0,"cad":0,"rub":0,"hkd":0,"jpy":0,"aud":0},"availableSupply":1524686,"volume24":{"usd":388.516,"btc":0,"eur":0,"cny":0,"gbp":0,"cad":0,"rub":0,"hkd":0,"jpy":0,"aud":0},"change1h":0,"change24h":45.17,"change7d":35.46,"timestamp":1532318405,"date":"23-07-2018"},"3":{"position":1272,"name":"Beatcoin","symbol":"XBTS","identifier":"beatcoin","category":"currency","marketCap":{"usd":95302,"btc":0,"eur":0,"cny":0,"gbp":0,"cad":0,"rub":0,"hkd":0,"jpy":0,"aud":0},"price":{"usd":0.0625058,"btc":0,"eur":0,"cny":0,"cad":0,"rub":0,"hkd":0,"jpy":0,"aud":0},"availableSupply":1524686,"volume24":{"usd":390.002,"btc":0,"eur":0,"cny":0,"gbp":0,"cad":0,"rub":0,"hkd":0,"jpy":0,"aud":0},"change1h":0.45,"change24h":30.01,"change7d":35.87,"timestamp":1532319904,"date":"23-07-2018"},"4":{"position":1272,"name":"Beatcoin","symbol":"XBTS","identifier":"beatcoin","category":"currency","marketCap":{"usd":95555,"btc":0,"eur":0,"cny":0,"gbp":0,"cad":0,"rub":0,"hkd":0,"jpy":0,"aud":0},"price":{"usd":0.0626718,"btc":0,"eur":0,"cny":0,"cad":0,"rub":0,"hkd":0,"jpy":0,"aud":0},"availableSupply":1524686,"volume24":{"usd":391.039,"btc":0,"eur":0,"cny":0,"gbp":0,"cad":0,"rub":0,"hkd":0,"jpy":0,"aud":0},"change1h":0.61,"change24h":17.6,"change7d":36.1,"timestamp":1532321404,"date":"23-07-2018"},"5":{"position":1272,"name":"Beatcoin","symbol":"XBTS","identifier":"beatcoin","category":"currency","marketCap":{"usd":95555,"btc":0,"eur":0,"cny":0,"gbp":0,"cad":0,"rub":0,"hkd":0,"jpy":0,"aud":0},"price":{"usd":0.0626718,"btc":0,"eur":0,"cny":0,"cad":0,"rub":0,"hkd":0,"jpy":0,"aud":0},"availableSupply":1524686,"volume24":{"usd":391.039,"btc":0,"eur":0,"cny":0,"gbp":0,"cad":0,"rub":0,"hkd":0,"jpy":0,"aud":0},"change1h":0.61,"change24h":17.6,"change7d":36.1,"timestamp":1532322008,"date":"23-07-2018"},"6":{"position":1271,"name":"Beatcoin","symbol":"XBTS","identifier":"beatcoin","category":"currency","marketCap":{"usd":95380,"btc":0,"eur":0,"cny":0,"gbp":0,"cad":0,"rub":0,"hkd":0,"jpy":0,"aud":0},"price":{"usd":0.0625571,"btc":0,"eur":0,"cny":0,"cad":0,"rub":0,"hkd":0,"jpy":0,"aud":0},"availableSupply":1524686,"volume24":{"usd":390.323,"btc":0,"eur":0,"cny":0,"gbp":0,"cad":0,"rub":0,"hkd":0,"jpy":0,"aud":0},"change1h":0.32,"change24h":6.95,"change7d":35.71,"timestamp":1532323507,"date":"23-07-2018"},"7":{"position":1272,"name":"Beatcoin","symbol":"XBTS","identifier":"beatcoin","category":"currency","marketCap":{"usd":95375,"btc":0,"eur":0,"cny":0,"gbp":0,"cad":0,"rub":0,"hkd":0,"jpy":0,"aud":0},"price":{"usd":0.062554,"btc":0,"eur":0,"cny":0,"cad":0,"rub":0,"hkd":0,"jpy":0,"aud":0},"availableSupply":1524686,"volume24":{"usd":390.304,"btc":0,"eur":0,"cny":0,"gbp":0,"cad":0,"rub":0,"hkd":0,"jpy":0,"aud":0},"change1h":-0.19,"change24h":-0.43,"change7d":35.51,"timestamp":1532325004,"date":"23-07-2018"},"8":{"position":1272,"name":"Beatcoin","symbol":"XBTS","identifier":"beatcoin","category":"currency","marketCap":{"usd":95375,"btc":0,"eur":0,"cny":0,"gbp":0,"cad":0,"rub":0,"hkd":0,"jpy":0,"aud":0},"price":{"usd":0.062554,"btc":0,"eur":0,"cny":0,"cad":0,"rub":0,"hkd":0,"jpy":0,"aud":0},"availableSupply":1524686,"volume24":{"usd":390.304,"btc":0,"eur":0,"cny":0,"gbp":0,"cad":0,"rub":0,"hkd":0,"jpy":0,"aud":0},"change1h":-0.19,"change24h":-0.43,"change7d":35.51,"timestamp":1532325604,"date":"23-07-2018"},"9":{"position":1273,"name":"Beatcoin","symbol":"XBTS","identifier":"beatcoin","category":"currency","marketCap":{"usd":95278,"btc":0,"eur":0,"cny":0,"gbp":0,"cad":0,"rub":0,"hkd":0,"jpy":0,"aud":0},"price":{"usd":0.0624901,"btc":0,"eur":0,"cny":0,"cad":0,"rub":0,"hkd":0,"jpy":0,"aud":0},"availableSupply":1524686,"volume24":{"usd":377.517,"btc":0,"eur":0,"cny":0,"gbp":0,"cad":0,"rub":0,"hkd":0,"jpy":0,"aud":0},"change1h":-0.04,"change24h":-0.51,"change7d":35.16,"timestamp":1532327112,"date":"23-07-2018"},"10":{"position":1271,"name":"Beatcoin","symbol":"XBTS","identifier":"beatcoin","category":"currency","marketCap":{"usd":95297,"btc":0,"eur":0,"cny":0,"gbp":0,"cad":0,"rub":0,"hkd":0,"jpy":0,"aud":0},"price":{"usd":0.0625025,"btc":0,"eur":0,"cny":0,"cad":0,"rub":0,"hkd":0,"jpy":0,"aud":0},"availableSupply":1524686,"volume24":{"usd":377.592,"btc":0,"eur":0,"cny":0,"gbp":0,"cad":0,"rub":0,"hkd":0,"jpy":0,"aud":0},"change1h":0.04,"change24h":-0.49,"change7d":34.99,"timestamp":1532328608,"date":"23-07-2018"}},"s":{"price":{"gbp":[0,0,0,0,0,0,0,0,0]}}}}