{"data":{"0":null,"symbol":["C20","C20","C20","C20","C20","C20","C20","C20","C20"],"history":{"2":{"position":190,"name":"CRYPTO20","symbol":"C20","identifier":"c20","category":"currency","marketCap":{"usd":38942600,"btc":0,"eur":0,"cny":0,"gbp":0,"cad":0,"rub":0,"hkd":0,"jpy":0,"aud":0},"price":{"usd":0.964557,"btc":0,"eur":0,"cny":0,"cad":0,"rub":0,"hkd":0,"jpy":0,"aud":0},"availableSupply":40373560,"volume24":{"usd":35260.7,"btc":0,"eur":0,"cny":0,"gbp":0,"cad":0,"rub":0,"hkd":0,"jpy":0,"aud":0},"change1h":-6.03,"change24h":-5.27,"change7d":2.69,"timestamp":1532318403,"date":"23-07-2018"},"3":{"position":187,"name":"CRYPTO20","symbol":"C20","identifier":"c20","category":"currency","marketCap":{"usd":38976070,"btc":0,"eur":0,"cny":0,"gbp":0,"cad":0,"rub":0,"hkd":0,"jpy":0,"aud":0},"price":{"usd":0.965386,"btc":0,"eur":0,"cny":0,"cad":0,"rub":0,"hkd":0,"jpy":0,"aud":0},"availableSupply":40373560,"volume24":{"usd":34999.5,"btc":0,"eur":0,"cny":0,"gbp":0,"cad":0,"rub":0,"hkd":0,"jpy":0,"aud":0},"change1h":-5.43,"change24h":-5.17,"change7d":2.88,"timestamp":1532319902,"date":"23-07-2018"},"4":{"position":188,"name":"CRYPTO20","symbol":"C20","identifier":"c20","category":"currency","marketCap":{"usd":39131912,"btc":0,"eur":0,"cny":0,"gbp":0,"cad":0,"rub":0,"hkd":0,"jpy":0,"aud":0},"price":{"usd":0.969246,"btc":0,"eur":0,"cny":0,"cad":0,"rub":0,"hkd":0,"jpy":0,"aud":0},"availableSupply":40373560,"volume24":{"usd":35097.2,"btc":0,"eur":0,"cny":0,"gbp":0,"cad":0,"rub":0,"hkd":0,"jpy":0,"aud":0},"change1h":0.48,"change24h":-4.89,"change7d":3.47,"timestamp":1532321402,"date":"23-07-2018"},"5":{"position":188,"name":"CRYPTO20","symbol":"C20","identifier":"c20","category":"currency","marketCap":{"usd":39131912,"btc":0,"eur":0,"cny":0,"gbp":0,"cad":0,"rub":0,"hkd":0,"jpy":0,"aud":0},"price":{"usd":0.969246,"btc":0,"eur":0,"cny":0,"cad":0,"rub":0,"hkd":0,"jpy":0,"aud":0},"availableSupply":40373560,"volume24":{"usd":35097.2,"btc":0,"eur":0,"cny":0,"gbp":0,"cad":0,"rub":0,"hkd":0,"jpy":0,"aud":0},"change1h":0.48,"change24h":-4.89,"change7d":3.47,"timestamp":1532322002,"date":"23-07-2018"},"6":{"position":186,"name":"CRYPTO20","symbol":"C20","identifier":"c20","category":"currency","marketCap":{"usd":39553613,"btc":0,"eur":0,"cny":0,"gbp":0,"cad":0,"rub":0,"hkd":0,"jpy":0,"aud":0},"price":{"usd":0.979691,"btc":0,"eur":0,"cny":0,"cad":0,"rub":0,"hkd":0,"jpy":0,"aud":0},"availableSupply":40373560,"volume24":{"usd":34926.2,"btc":0,"eur":0,"cny":0,"gbp":0,"cad":0,"rub":0,"hkd":0,"jpy":0,"aud":0},"change1h":1.52,"change24h":-3.94,"change7d":4.69,"timestamp":1532323502,"date":"23-07-2018"},"7":{"position":185,"name":"CRYPTO20","symbol":"C20","identifier":"c20","category":"currency","marketCap":{"usd":39525836,"btc":0,"eur":0,"cny":0,"gbp":0,"cad":0,"rub":0,"hkd":0,"jpy":0,"aud":0},"price":{"usd":0.979003,"btc":0,"eur":0,"cny":0,"cad":0,"rub":0,"hkd":0,"jpy":0,"aud":0},"availableSupply":40373560,"volume24":{"usd":34811.2,"btc":0,"eur":0,"cny":0,"gbp":0,"cad":0,"rub":0,"hkd":0,"jpy":0,"aud":0},"change1h":1.12,"change24h":-4.08,"change7d":4.66,"timestamp":1532325002,"date":"23-07-2018"},"8":{"position":185,"name":"CRYPTO20","symbol":"C20","identifier":"c20","category":"currency","marketCap":{"usd":39525836,"btc":0,"eur":0,"cny":0,"gbp":0,"cad":0,"rub":0,"hkd":0,"jpy":0,"aud":0},"price":{"usd":0.979003,"btc":0,"eur":0,"cny":0,"cad":0,"rub":0,"hkd":0,"jpy":0,"aud":0},"availableSupply":40373560,"volume24":{"usd":34811.2,"btc":0,"eur":0,"cny":0,"gbp":0,"cad":0,"rub":0,"hkd":0,"jpy":0,"aud":0},"change1h":1.12,"change24h":-4.08,"change7d":4.66,"timestamp":1532325602,"date":"23-07-2018"},"9":{"position":184,"name":"CRYPTO20","symbol":"C20","identifier":"c20","category":"currency","marketCap":{"usd":40194786,"btc":0,"eur":0,"cny":0,"gbp":0,"cad":0,"rub":0,"hkd":0,"jpy":0,"aud":0},"price":{"usd":0.995572,"btc":0,"eur":0,"cny":0,"cad":0,"rub":0,"hkd":0,"jpy":0,"aud":0},"availableSupply":40373560,"volume24":{"usd":34406,"btc":0,"eur":0,"cny":0,"gbp":0,"cad":0,"rub":0,"hkd":0,"jpy":0,"aud":0},"change1h":1.84,"change24h":-2.52,"change7d":6.31,"timestamp":1532327105,"date":"23-07-2018"},"10":{"position":179,"name":"CRYPTO20","symbol":"C20","identifier":"c20","category":"currency","marketCap":{"usd":41539952,"btc":0,"eur":0,"cny":0,"gbp":0,"cad":0,"rub":0,"hkd":0,"jpy":0,"aud":0},"price":{"usd":1.02889,"btc":0,"eur":0,"cny":0,"cad":0,"rub":0,"hkd":0,"jpy":0,"aud":0},"availableSupply":40373560,"volume24":{"usd":35952.1,"btc":0,"eur":0,"cny":0,"gbp":0,"cad":0,"rub":0,"hkd":0,"jpy":0,"aud":0},"change1h":5.12,"change24h":0.77,"change7d":9.79,"timestamp":1532328601,"date":"23-07-2018"}},"s":{"price":{"gbp":[0,0,0,0,0,0,0,0,0]}}}}