{"data":{"0":null,"symbol":"MCR","history":{"2":{"position":1462,"name":"Macro","symbol":"MCR","identifier":"macro1","category":"currency","marketCap":{"usd":null,"btc":0,"eur":0,"cny":0,"gbp":0,"cad":0,"rub":0,"hkd":0,"jpy":0,"aud":0},"price":{"usd":0.203559,"btc":0,"eur":0,"cny":0,"cad":0,"rub":0,"hkd":0,"jpy":0,"aud":0},"availableSupply":null,"volume24":{"usd":4150.76,"btc":0,"eur":0,"cny":0,"gbp":0,"cad":0,"rub":0,"hkd":0,"jpy":0,"aud":0},"change1h":-0.13,"change24h":4.22,"change7d":-79.61,"timestamp":1530557799,"date":"02-07-2018"}},"s":{"price":{"gbp":0}}}}