{"data":{"0":null,"symbol":["PIE","PIE","PIE","PIE","PIE","PIE","PIE","PIE"],"history":{"2":{"position":1332,"name":"PIECoin","symbol":"PIE","identifier":"piecoin","category":"currency","marketCap":{"usd":40393,"btc":0,"eur":0,"cny":0,"gbp":0,"cad":0,"rub":0,"hkd":0,"jpy":0,"aud":0},"price":{"usd":0.00365459,"btc":0,"eur":0,"cny":0,"cad":0,"rub":0,"hkd":0,"jpy":0,"aud":0},"availableSupply":11052595,"volume24":{"usd":11.6838,"btc":0,"eur":0,"cny":0,"gbp":0,"cad":0,"rub":0,"hkd":0,"jpy":0,"aud":0},"change1h":0,"change24h":2.74,"change7d":29.92,"timestamp":1532318405,"date":"23-07-2018"},"3":{"position":1332,"name":"PIECoin","symbol":"PIE","identifier":"piecoin","category":"currency","marketCap":{"usd":40547,"btc":0,"eur":0,"cny":0,"gbp":0,"cad":0,"rub":0,"hkd":0,"jpy":0,"aud":0},"price":{"usd":0.00366857,"btc":0,"eur":0,"cny":0,"cad":0,"rub":0,"hkd":0,"jpy":0,"aud":0},"availableSupply":11052595,"volume24":{"usd":11.7285,"btc":0,"eur":0,"cny":0,"gbp":0,"cad":0,"rub":0,"hkd":0,"jpy":0,"aud":0},"change1h":0.45,"change24h":3.25,"change7d":null,"timestamp":1532319904,"date":"23-07-2018"},"4":{"position":1332,"name":"PIECoin","symbol":"PIE","identifier":"piecoin","category":"currency","marketCap":{"usd":40655,"btc":0,"eur":0,"cny":0,"gbp":0,"cad":0,"rub":0,"hkd":0,"jpy":0,"aud":0},"price":{"usd":0.00367831,"btc":0,"eur":0,"cny":0,"cad":0,"rub":0,"hkd":0,"jpy":0,"aud":0},"availableSupply":11052595,"volume24":{"usd":11.7596,"btc":0,"eur":0,"cny":0,"gbp":0,"cad":0,"rub":0,"hkd":0,"jpy":0,"aud":0},"change1h":0.61,"change24h":3.56,"change7d":null,"timestamp":1532321404,"date":"23-07-2018"},"5":{"position":1332,"name":"PIECoin","symbol":"PIE","identifier":"piecoin","category":"currency","marketCap":{"usd":40655,"btc":0,"eur":0,"cny":0,"gbp":0,"cad":0,"rub":0,"hkd":0,"jpy":0,"aud":0},"price":{"usd":0.00367831,"btc":0,"eur":0,"cny":0,"cad":0,"rub":0,"hkd":0,"jpy":0,"aud":0},"availableSupply":11052595,"volume24":{"usd":11.7596,"btc":0,"eur":0,"cny":0,"gbp":0,"cad":0,"rub":0,"hkd":0,"jpy":0,"aud":0},"change1h":0.61,"change24h":3.56,"change7d":null,"timestamp":1532322008,"date":"23-07-2018"},"6":{"position":1330,"name":"PIECoin","symbol":"PIE","identifier":"piecoin","category":"currency","marketCap":{"usd":40580,"btc":0,"eur":0,"cny":0,"gbp":0,"cad":0,"rub":0,"hkd":0,"jpy":0,"aud":0},"price":{"usd":0.00367158,"btc":0,"eur":0,"cny":0,"cad":0,"rub":0,"hkd":0,"jpy":0,"aud":0},"availableSupply":11052595,"volume24":{"usd":11.7381,"btc":0,"eur":0,"cny":0,"gbp":0,"cad":0,"rub":0,"hkd":0,"jpy":0,"aud":0},"change1h":0.32,"change24h":3.44,"change7d":null,"timestamp":1532323507,"date":"23-07-2018"},"7":{"position":1330,"name":"PIECoin","symbol":"PIE","identifier":"piecoin","category":"currency","marketCap":{"usd":40604,"btc":0,"eur":0,"cny":0,"gbp":0,"cad":0,"rub":0,"hkd":0,"jpy":0,"aud":0},"price":{"usd":0.00367367,"btc":0,"eur":0,"cny":0,"cad":0,"rub":0,"hkd":0,"jpy":0,"aud":0},"availableSupply":11052595,"volume24":{"usd":null,"btc":0,"eur":0,"cny":0,"gbp":0,"cad":0,"rub":0,"hkd":0,"jpy":0,"aud":0},"change1h":-0.13,"change24h":3.55,"change7d":null,"timestamp":1532325004,"date":"23-07-2018"},"8":{"position":1330,"name":"PIECoin","symbol":"PIE","identifier":"piecoin","category":"currency","marketCap":{"usd":40604,"btc":0,"eur":0,"cny":0,"gbp":0,"cad":0,"rub":0,"hkd":0,"jpy":0,"aud":0},"price":{"usd":0.00367367,"btc":0,"eur":0,"cny":0,"cad":0,"rub":0,"hkd":0,"jpy":0,"aud":0},"availableSupply":11052595,"volume24":{"usd":null,"btc":0,"eur":0,"cny":0,"gbp":0,"cad":0,"rub":0,"hkd":0,"jpy":0,"aud":0},"change1h":-0.13,"change24h":3.55,"change7d":null,"timestamp":1532325604,"date":"23-07-2018"},"9":{"position":1331,"name":"PIECoin","symbol":"PIE","identifier":"piecoin","category":"currency","marketCap":{"usd":40604,"btc":0,"eur":0,"cny":0,"gbp":0,"cad":0,"rub":0,"hkd":0,"jpy":0,"aud":0},"price":{"usd":0.00367367,"btc":0,"eur":0,"cny":0,"cad":0,"rub":0,"hkd":0,"jpy":0,"aud":0},"availableSupply":11052595,"volume24":{"usd":null,"btc":0,"eur":0,"cny":0,"gbp":0,"cad":0,"rub":0,"hkd":0,"jpy":0,"aud":0},"change1h":0.12,"change24h":3.57,"change7d":null,"timestamp":1532327112,"date":"23-07-2018"}},"s":{"price":{"gbp":[0,0,0,0,0,0,0,0]}}}}