{"data":{"0":null,"symbol":["XRY","XRY","XRY","XRY","XRY","XRY","XRY","XRY"],"history":{"2":{"position":1548,"name":"Royalties","symbol":"XRY","identifier":"royalties","category":"currency","marketCap":{"usd":null,"btc":0,"eur":0,"cny":0,"gbp":0,"cad":0,"rub":0,"hkd":0,"jpy":0,"aud":0},"price":{"usd":2.11941e-5,"btc":0,"eur":0,"cny":0,"cad":0,"rub":0,"hkd":0,"jpy":0,"aud":0},"availableSupply":null,"volume24":{"usd":598.439,"btc":0,"eur":0,"cny":0,"gbp":0,"cad":0,"rub":0,"hkd":0,"jpy":0,"aud":0},"change1h":0,"change24h":102.5,"change7d":-50.42,"timestamp":1532318406,"date":"23-07-2018"},"3":{"position":1550,"name":"Royalties","symbol":"XRY","identifier":"royalties","category":"currency","marketCap":{"usd":null,"btc":0,"eur":0,"cny":0,"gbp":0,"cad":0,"rub":0,"hkd":0,"jpy":0,"aud":0},"price":{"usd":2.12808e-5,"btc":0,"eur":0,"cny":0,"cad":0,"rub":0,"hkd":0,"jpy":0,"aud":0},"availableSupply":null,"volume24":{"usd":599.899,"btc":0,"eur":0,"cny":0,"gbp":0,"cad":0,"rub":0,"hkd":0,"jpy":0,"aud":0},"change1h":0.47,"change24h":89.06,"change7d":-51.14,"timestamp":1532319905,"date":"23-07-2018"},"4":{"position":1556,"name":"Royalties","symbol":"XRY","identifier":"royalties","category":"currency","marketCap":{"usd":null,"btc":0,"eur":0,"cny":0,"gbp":0,"cad":0,"rub":0,"hkd":0,"jpy":0,"aud":0},"price":{"usd":8.5929e-6,"btc":0,"eur":0,"cny":0,"cad":0,"rub":0,"hkd":0,"jpy":0,"aud":0},"availableSupply":null,"volume24":{"usd":486.914,"btc":0,"eur":0,"cny":0,"gbp":0,"cad":0,"rub":0,"hkd":0,"jpy":0,"aud":0},"change1h":-59.48,"change24h":-28.36,"change7d":-80.64,"timestamp":1532321405,"date":"23-07-2018"},"5":{"position":1556,"name":"Royalties","symbol":"XRY","identifier":"royalties","category":"currency","marketCap":{"usd":null,"btc":0,"eur":0,"cny":0,"gbp":0,"cad":0,"rub":0,"hkd":0,"jpy":0,"aud":0},"price":{"usd":8.5929e-6,"btc":0,"eur":0,"cny":0,"cad":0,"rub":0,"hkd":0,"jpy":0,"aud":0},"availableSupply":null,"volume24":{"usd":486.914,"btc":0,"eur":0,"cny":0,"gbp":0,"cad":0,"rub":0,"hkd":0,"jpy":0,"aud":0},"change1h":-59.48,"change24h":-28.36,"change7d":-80.64,"timestamp":1532322008,"date":"23-07-2018"},"6":{"position":1556,"name":"Royalties","symbol":"XRY","identifier":"royalties","category":"currency","marketCap":{"usd":null,"btc":0,"eur":0,"cny":0,"gbp":0,"cad":0,"rub":0,"hkd":0,"jpy":0,"aud":0},"price":{"usd":8.5961e-6,"btc":0,"eur":0,"cny":0,"cad":0,"rub":0,"hkd":0,"jpy":0,"aud":0},"availableSupply":null,"volume24":{"usd":487.094,"btc":0,"eur":0,"cny":0,"gbp":0,"cad":0,"rub":0,"hkd":0,"jpy":0,"aud":0},"change1h":-59.5,"change24h":-32.5,"change7d":-80.98,"timestamp":1532323508,"date":"23-07-2018"},"7":{"position":1555,"name":"Royalties","symbol":"XRY","identifier":"royalties","category":"currency","marketCap":{"usd":null,"btc":0,"eur":0,"cny":0,"gbp":0,"cad":0,"rub":0,"hkd":0,"jpy":0,"aud":0},"price":{"usd":8.5634e-6,"btc":0,"eur":0,"cny":0,"cad":0,"rub":0,"hkd":0,"jpy":0,"aud":0},"availableSupply":null,"volume24":{"usd":485.24,"btc":0,"eur":0,"cny":0,"gbp":0,"cad":0,"rub":0,"hkd":0,"jpy":0,"aud":0},"change1h":-0.23,"change24h":-36.36,"change7d":-81.4,"timestamp":1532325005,"date":"23-07-2018"},"8":{"position":1555,"name":"Royalties","symbol":"XRY","identifier":"royalties","category":"currency","marketCap":{"usd":null,"btc":0,"eur":0,"cny":0,"gbp":0,"cad":0,"rub":0,"hkd":0,"jpy":0,"aud":0},"price":{"usd":8.5634e-6,"btc":0,"eur":0,"cny":0,"cad":0,"rub":0,"hkd":0,"jpy":0,"aud":0},"availableSupply":null,"volume24":{"usd":485.24,"btc":0,"eur":0,"cny":0,"gbp":0,"cad":0,"rub":0,"hkd":0,"jpy":0,"aud":0},"change1h":-0.23,"change24h":-36.36,"change7d":-81.4,"timestamp":1532325605,"date":"23-07-2018"},"9":{"position":1555,"name":"Royalties","symbol":"XRY","identifier":"royalties","category":"currency","marketCap":{"usd":null,"btc":0,"eur":0,"cny":0,"gbp":0,"cad":0,"rub":0,"hkd":0,"jpy":0,"aud":0},"price":{"usd":8.5671e-6,"btc":0,"eur":0,"cny":0,"cad":0,"rub":0,"hkd":0,"jpy":0,"aud":0},"availableSupply":null,"volume24":{"usd":485.45,"btc":0,"eur":0,"cny":0,"gbp":0,"cad":0,"rub":0,"hkd":0,"jpy":0,"aud":0},"change1h":-0.13,"change24h":-38.34,"change7d":-81.73,"timestamp":1532327113,"date":"23-07-2018"}},"s":{"price":{"gbp":[0,0,0,0,0,0,0,0]}}}}