{"data":{"0":null,"symbol":["ZMC","ZMC","ZMC","ZMC","ZMC","ZMC","ZMC","ZMC"],"history":{"2":{"position":1324,"name":"ZetaMicron","symbol":"ZMC","identifier":"zetamicron","category":"currency","marketCap":{"usd":45709,"btc":0,"eur":0,"cny":0,"gbp":0,"cad":0,"rub":0,"hkd":0,"jpy":0,"aud":0},"price":{"usd":7.61373e-5,"btc":0,"eur":0,"cny":0,"cad":0,"rub":0,"hkd":0,"jpy":0,"aud":0},"availableSupply":600344291,"volume24":{"usd":2.66481,"btc":0,"eur":0,"cny":0,"gbp":0,"cad":0,"rub":0,"hkd":0,"jpy":0,"aud":0},"change1h":null,"change24h":2.74,"change7d":19.49,"timestamp":1532318405,"date":"23-07-2018"},"3":{"position":1324,"name":"ZetaMicron","symbol":"ZMC","identifier":"zetamicron","category":"currency","marketCap":{"usd":45883,"btc":0,"eur":0,"cny":0,"gbp":0,"cad":0,"rub":0,"hkd":0,"jpy":0,"aud":0},"price":{"usd":7.64285e-5,"btc":0,"eur":0,"cny":0,"cad":0,"rub":0,"hkd":0,"jpy":0,"aud":0},"availableSupply":600344291,"volume24":{"usd":2.675,"btc":0,"eur":0,"cny":0,"gbp":0,"cad":0,"rub":0,"hkd":0,"jpy":0,"aud":0},"change1h":null,"change24h":3.25,"change7d":19.97,"timestamp":1532319904,"date":"23-07-2018"},"4":{"position":1324,"name":"ZetaMicron","symbol":"ZMC","identifier":"zetamicron","category":"currency","marketCap":{"usd":46005,"btc":0,"eur":0,"cny":0,"gbp":0,"cad":0,"rub":0,"hkd":0,"jpy":0,"aud":0},"price":{"usd":7.66316e-5,"btc":0,"eur":0,"cny":0,"cad":0,"rub":0,"hkd":0,"jpy":0,"aud":0},"availableSupply":600344291,"volume24":{"usd":8.60572,"btc":0,"eur":0,"cny":0,"gbp":0,"cad":0,"rub":0,"hkd":0,"jpy":0,"aud":0},"change1h":0.66,"change24h":3.56,"change7d":20.3,"timestamp":1532321404,"date":"23-07-2018"},"5":{"position":1324,"name":"ZetaMicron","symbol":"ZMC","identifier":"zetamicron","category":"currency","marketCap":{"usd":46005,"btc":0,"eur":0,"cny":0,"gbp":0,"cad":0,"rub":0,"hkd":0,"jpy":0,"aud":0},"price":{"usd":7.66316e-5,"btc":0,"eur":0,"cny":0,"cad":0,"rub":0,"hkd":0,"jpy":0,"aud":0},"availableSupply":600344291,"volume24":{"usd":8.60572,"btc":0,"eur":0,"cny":0,"gbp":0,"cad":0,"rub":0,"hkd":0,"jpy":0,"aud":0},"change1h":0.66,"change24h":3.56,"change7d":20.3,"timestamp":1532322008,"date":"23-07-2018"},"6":{"position":1322,"name":"ZetaMicron","symbol":"ZMC","identifier":"zetamicron","category":"currency","marketCap":{"usd":45921,"btc":0,"eur":0,"cny":0,"gbp":0,"cad":0,"rub":0,"hkd":0,"jpy":0,"aud":0},"price":{"usd":7.64913e-5,"btc":0,"eur":0,"cny":0,"cad":0,"rub":0,"hkd":0,"jpy":0,"aud":0},"availableSupply":600344291,"volume24":{"usd":8.58997,"btc":0,"eur":0,"cny":0,"gbp":0,"cad":0,"rub":0,"hkd":0,"jpy":0,"aud":0},"change1h":0.32,"change24h":3.43,"change7d":20.09,"timestamp":1532323507,"date":"23-07-2018"},"7":{"position":1323,"name":"ZetaMicron","symbol":"ZMC","identifier":"zetamicron","category":"currency","marketCap":{"usd":45919,"btc":0,"eur":0,"cny":0,"gbp":0,"cad":0,"rub":0,"hkd":0,"jpy":0,"aud":0},"price":{"usd":7.64875e-5,"btc":0,"eur":0,"cny":0,"cad":0,"rub":0,"hkd":0,"jpy":0,"aud":0},"availableSupply":600344291,"volume24":{"usd":8.58955,"btc":0,"eur":0,"cny":0,"gbp":0,"cad":0,"rub":0,"hkd":0,"jpy":0,"aud":0},"change1h":-0.19,"change24h":3.49,"change7d":20.09,"timestamp":1532325004,"date":"23-07-2018"},"8":{"position":1323,"name":"ZetaMicron","symbol":"ZMC","identifier":"zetamicron","category":"currency","marketCap":{"usd":45919,"btc":0,"eur":0,"cny":0,"gbp":0,"cad":0,"rub":0,"hkd":0,"jpy":0,"aud":0},"price":{"usd":7.64875e-5,"btc":0,"eur":0,"cny":0,"cad":0,"rub":0,"hkd":0,"jpy":0,"aud":0},"availableSupply":600344291,"volume24":{"usd":8.58955,"btc":0,"eur":0,"cny":0,"gbp":0,"cad":0,"rub":0,"hkd":0,"jpy":0,"aud":0},"change1h":-0.19,"change24h":3.49,"change7d":20.09,"timestamp":1532325604,"date":"23-07-2018"},"9":{"position":1325,"name":"ZetaMicron","symbol":"ZMC","identifier":"zetamicron","category":"currency","marketCap":{"usd":45932,"btc":0,"eur":0,"cny":0,"gbp":0,"cad":0,"rub":0,"hkd":0,"jpy":0,"aud":0},"price":{"usd":7.6509e-5,"btc":0,"eur":0,"cny":0,"cad":0,"rub":0,"hkd":0,"jpy":0,"aud":0},"availableSupply":600344291,"volume24":{"usd":8.59196,"btc":0,"eur":0,"cny":0,"gbp":0,"cad":0,"rub":0,"hkd":0,"jpy":0,"aud":0},"change1h":0.09,"change24h":3.53,"change7d":20.11,"timestamp":1532327112,"date":"23-07-2018"}},"s":{"price":{"gbp":[0,0,0,0,0,0,0,0]}}}}