{"data":{"data":{"2672":{"id":2672,"name":"SRCOIN","symbol":"SRCOIN","website_slug":"srcoin","rank":600,"circulating_supply":5052048084,"total_supply":15000000000,"max_supply":null,"quotes":{"USD":{"price":0.000911572,"volume_24h":788258,"market_cap":4605306,"percent_change_1h":0.62,"percent_change_24h":6.07,"percent_change_7d":-19.03}},"last_updated":1532328286},"2105":{"id":2105,"name":"Pirl","symbol":"PIRL","website_slug":"pirl","rank":601,"circulating_supply":22091266,"total_supply":22091266,"max_supply":null,"quotes":{"USD":{"price":0.207604,"volume_24h":29356.5,"market_cap":4586235,"percent_change_1h":-0.1,"percent_change_24h":4.4,"percent_change_7d":9.21}},"last_updated":1532328279},"2547":{"id":2547,"name":"Experty","symbol":"EXY","website_slug":"experty","rank":602,"circulating_supply":27088352,"total_supply":79404564,"max_supply":null,"quotes":{"USD":{"price":0.168405,"volume_24h":169250,"market_cap":4561814,"percent_change_1h":0,"percent_change_24h":10.89,"percent_change_7d":7.42}},"last_updated":1532328283},"2204":{"id":2204,"name":"B2BX","symbol":"B2B","website_slug":"b2bx","rank":603,"circulating_supply":16350644,"total_supply":19822337,"max_supply":null,"quotes":{"USD":{"price":0.278066,"volume_24h":101604,"market_cap":4546558,"percent_change_1h":1.38,"percent_change_24h":0.76,"percent_change_7d":4.72}},"last_updated":1532328279},"2374":{"id":2374,"name":"BitDegree","symbol":"BDG","website_slug":"bitdegree","rank":604,"circulating_supply":355338365,"total_supply":514800000,"max_supply":null,"quotes":{"USD":{"price":0.0127822,"volume_24h":3656,"market_cap":4542006,"percent_change_1h":0.57,"percent_change_24h":10.28,"percent_change_7d":-1.46}},"last_updated":1532328286},"1527":{"id":1527,"name":"Waves Community Token","symbol":"WCT","website_slug":"waves-community-token","rank":605,"circulating_supply":9964596,"total_supply":9999999,"max_supply":null,"quotes":{"USD":{"price":0.454436,"volume_24h":5913.45,"market_cap":4528271,"percent_change_1h":-0.61,"percent_change_24h":-0.04,"percent_change_7d":-1.35}},"last_updated":1532328274},"2758":{"id":2758,"name":"Unibright","symbol":"UBT","website_slug":"unibright","rank":606,"circulating_supply":135195122,"total_supply":150000000,"max_supply":null,"quotes":{"USD":{"price":0.0333011,"volume_24h":95133.7,"market_cap":4502146,"percent_change_1h":-0.76,"percent_change_24h":2.2,"percent_change_7d":-9.02}},"last_updated":1532328288},"2325":{"id":2325,"name":"Matryx","symbol":"MTX","website_slug":"matryx","rank":607,"circulating_supply":23224303,"total_supply":314159265,"max_supply":null,"quotes":{"USD":{"price":0.192352,"volume_24h":198826,"market_cap":4467241,"percent_change_1h":-0.76,"percent_change_24h":-1.86,"percent_change_7d":-10.28}},"last_updated":1532328281},"2066":{"id":2066,"name":"Everus","symbol":"EVR","website_slug":"everus","rank":608,"circulating_supply":151133508,"total_supply":1000000000,"max_supply":null,"quotes":{"USD":{"price":0.029519,"volume_24h":227278,"market_cap":4461310,"percent_change_1h":0.17,"percent_change_24h":1.74,"percent_change_7d":9.26}},"last_updated":1532328276},"322":{"id":322,"name":"Energycoin","symbol":"ENRG","website_slug":"energycoin","rank":609,"circulating_supply":122059872,"total_supply":122059872,"max_supply":null,"quotes":{"USD":{"price":0.0362724,"volume_24h":7873.86,"market_cap":4427405,"percent_change_1h":0.17,"percent_change_24h":-1.98,"percent_change_7d":11.49}},"last_updated":1532328265},"2422":{"id":2422,"name":"IDEX Membership","symbol":"IDXM","website_slug":"idex-membership","rank":610,"circulating_supply":2000,"total_supply":2000,"max_supply":null,"quotes":{"USD":{"price":2209.81,"volume_24h":9147.66,"market_cap":4419620,"percent_change_1h":-0.11,"percent_change_24h":-9.39,"percent_change_7d":1.17}},"last_updated":1532328281},"895":{"id":895,"name":"Xaurum","symbol":"XAUR","website_slug":"xaurum","rank":611,"circulating_supply":127132844,"total_supply":127132844,"max_supply":null,"quotes":{"USD":{"price":0.0346488,"volume_24h":3256.72,"market_cap":4405000,"percent_change_1h":-11.95,"percent_change_24h":-10.72,"percent_change_7d":-6.4}},"last_updated":1532328268},"2200":{"id":2200,"name":"GoByte","symbol":"GBX","website_slug":"gobyte","rank":612,"circulating_supply":2062733,"total_supply":2887720,"max_supply":31800000,"quotes":{"USD":{"price":2.11928,"volume_24h":31663.8,"market_cap":4371509,"percent_change_1h":0.03,"percent_change_24h":-6.36,"percent_change_7d":16.1}},"last_updated":1532328282},"2490":{"id":2490,"name":"CargoX","symbol":"CXO","website_slug":"cargox","rank":613,"circulating_supply":129071409,"total_supply":215119016,"max_supply":null,"quotes":{"USD":{"price":0.0337809,"volume_24h":7841.55,"market_cap":4360148,"percent_change_1h":-0.06,"percent_change_24h":0.08,"percent_change_7d":1.1}},"last_updated":1532328289},"2709":{"id":2709,"name":"Morpheus Labs","symbol":"MITX","website_slug":"morpheus-labs","rank":614,"circulating_supply":176560198,"total_supply":800000000,"max_supply":null,"quotes":{"USD":{"price":0.0246373,"volume_24h":847707,"market_cap":4349967,"percent_change_1h":-2.62,"percent_change_24h":-5.51,"percent_change_7d":17.28}},"last_updated":1532328289},"313":{"id":313,"name":"PinkCoin","symbol":"PINK","website_slug":"pinkcoin","rank":615,"circulating_supply":381906699,"total_supply":392906699,"max_supply":null,"quotes":{"USD":{"price":0.0112974,"volume_24h":6651.27,"market_cap":4314553,"percent_change_1h":-1.33,"percent_change_24h":1.54,"percent_change_7d":3.99}},"last_updated":1532328265},"1905":{"id":1905,"name":"TrueFlip","symbol":"TFL","website_slug":"trueflip","rank":616,"circulating_supply":6247267,"total_supply":8924667,"max_supply":null,"quotes":{"USD":{"price":0.687786,"volume_24h":200780,"market_cap":4296783,"percent_change_1h":1.1,"percent_change_24h":1.9,"percent_change_7d":6.07}},"last_updated":1532328278},"2310":{"id":2310,"name":"Bounty0x","symbol":"BNTY","website_slug":"bounty0x","rank":617,"circulating_supply":177567948,"total_supply":500000000,"max_supply":null,"quotes":{"USD":{"price":0.0241934,"volume_24h":2844.78,"market_cap":4295972,"percent_change_1h":-1.25,"percent_change_24h":3.21,"percent_change_7d":-6.82}},"last_updated":1532328278},"2872":{"id":2872,"name":"EnergiToken","symbol":"ETK","website_slug":"energitoken","rank":618,"circulating_supply":1140027357,"total_supply":2500000000,"max_supply":null,"quotes":{"USD":{"price":0.0036831,"volume_24h":61160.8,"market_cap":4198835,"percent_change_1h":5.01,"percent_change_24h":-0.57,"percent_change_7d":-22.38}},"last_updated":1532328290},"2343":{"id":2343,"name":"CanYaCoin","symbol":"CAN","website_slug":"canyacoin","rank":619,"circulating_supply":42011624,"total_supply":95827000,"max_supply":null,"quotes":{"USD":{"price":0.0995738,"volume_24h":15346.9,"market_cap":4183257,"percent_change_1h":0.19,"percent_change_24h":1.9,"percent_change_7d":0.33}},"last_updated":1532328282},"1606":{"id":1606,"name":"Solaris","symbol":"XLR","website_slug":"solaris","rank":620,"circulating_supply":1462047,"total_supply":1489022,"max_supply":null,"quotes":{"USD":{"price":2.84897,"volume_24h":18019.2,"market_cap":4165327,"percent_change_1h":0.15,"percent_change_24h":-6.43,"percent_change_7d":-2.88}},"last_updated":1532328272},"2589":{"id":2589,"name":"Guaranteed Ethurance Token Extra","symbol":"GETX","website_slug":"guaranteed-ethurance-token-extra","rank":621,"circulating_supply":300000000,"total_supply":1000000000,"max_supply":null,"quotes":{"USD":{"price":0.0138756,"volume_24h":1841.67,"market_cap":4162680,"percent_change_1h":-3.71,"percent_change_24h":-14.69,"percent_change_7d":119.07}},"last_updated":1532328285},"2551":{"id":2551,"name":"Bezop","symbol":"BEZ","website_slug":"bezop","rank":622,"circulating_supply":54544834,"total_supply":89267250,"max_supply":null,"quotes":{"USD":{"price":0.076068,"volume_24h":507972,"market_cap":4149116,"percent_change_1h":-1.78,"percent_change_24h":-11.26,"percent_change_7d":-12.88}},"last_updated":1532328286},"2231":{"id":2231,"name":"Flixxo","symbol":"FLIXX","website_slug":"flixxo","rank":623,"circulating_supply":79671513,"total_supply":189151329,"max_supply":null,"quotes":{"USD":{"price":0.0520346,"volume_24h":358496,"market_cap":4145675,"percent_change_1h":0.02,"percent_change_24h":1.86,"percent_change_7d":9.3}},"last_updated":1532328284},"2680":{"id":2680,"name":"Helbiz","symbol":"HBZ","website_slug":"helbiz","rank":624,"circulating_supply":547522129,"total_supply":1005250000,"max_supply":null,"quotes":{"USD":{"price":0.00757,"volume_24h":1125010,"market_cap":4144743,"percent_change_1h":0.38,"percent_change_24h":1.48,"percent_change_7d":1.51}},"last_updated":1532328288},"1109":{"id":1109,"name":"Elite","symbol":"1337","website_slug":"1337coin","rank":625,"circulating_supply":26225731532,"total_supply":29028084647,"max_supply":null,"quotes":{"USD":{"price":0.000157372,"volume_24h":20311.9,"market_cap":4127196,"percent_change_1h":1.11,"percent_change_24h":-4.68,"percent_change_7d":55.52}},"last_updated":1532328267},"2897":{"id":2897,"name":"Clipper Coin","symbol":"CCCX","website_slug":"clipper-coin","rank":626,"circulating_supply":717846353,"total_supply":5000000000,"max_supply":null,"quotes":{"USD":{"price":0.0057044,"volume_24h":296967,"market_cap":4094883,"percent_change_1h":-1.2,"percent_change_24h":7.5,"percent_change_7d":11.29}},"last_updated":1532328289},"2744":{"id":2744,"name":"NPER","symbol":"NPER","website_slug":"nper","rank":627,"circulating_supply":49935730,"total_supply":250000000,"max_supply":null,"quotes":{"USD":{"price":0.0815972,"volume_24h":1281980,"market_cap":4074616,"percent_change_1h":-1.26,"percent_change_24h":-4.02,"percent_change_7d":-4.5}},"last_updated":1532328289},"2208":{"id":2208,"name":"EncrypGen","symbol":"DNA","website_slug":"encrypgen","rank":628,"circulating_supply":62219914,"total_supply":70978131,"max_supply":null,"quotes":{"USD":{"price":0.0653842,"volume_24h":31119.2,"market_cap":4068199,"percent_change_1h":0.01,"percent_change_24h":8.69,"percent_change_7d":7.8}},"last_updated":1532328282},"2677":{"id":2677,"name":"Linker Coin","symbol":"LNC","website_slug":"linker-coin","rank":629,"circulating_supply":112776150,"total_supply":500000000,"max_supply":null,"quotes":{"USD":{"price":0.0359663,"volume_24h":62268.2,"market_cap":4056141,"percent_change_1h":-1.23,"percent_change_24h":18.47,"percent_change_7d":7.41}},"last_updated":1532328286},"2624":{"id":2624,"name":"Sentinel Chain","symbol":"SENC","website_slug":"sentinel-chain","rank":630,"circulating_supply":197269666,"total_supply":500000000,"max_supply":null,"quotes":{"USD":{"price":0.0203757,"volume_24h":468535,"market_cap":4019508,"percent_change_1h":0.43,"percent_change_24h":-0.32,"percent_change_7d":-7.53}},"last_updated":1532328283},"1811":{"id":1811,"name":"Nimiq Exchange Token","symbol":"NET","website_slug":"nimiq-exchange-token","rank":631,"circulating_supply":10500000,"total_supply":10500000,"max_supply":null,"quotes":{"USD":{"price":0.381243,"volume_24h":140981,"market_cap":4003052,"percent_change_1h":0.61,"percent_change_24h":1.7,"percent_change_7d":1.02}},"last_updated":1532328275},"921":{"id":921,"name":"Universal Currency","symbol":"UNIT","website_slug":"universal-currency","rank":632,"circulating_supply":14542926,"total_supply":18642926,"max_supply":210000000,"quotes":{"USD":{"price":0.273555,"volume_24h":30631.5,"market_cap":3978290,"percent_change_1h":0.6,"percent_change_24h":-7.28,"percent_change_7d":48.53}},"last_updated":1532328266},"2637":{"id":2637,"name":"Fidelium","symbol":"FID","website_slug":"fidelium","rank":633,"circulating_supply":117782948,"total_supply":191421673,"max_supply":null,"quotes":{"USD":{"price":0.0335191,"volume_24h":34375.6,"market_cap":3947978,"percent_change_1h":0.17,"percent_change_24h":11.59,"percent_change_7d":-25.7}},"last_updated":1532328289},"2041":{"id":2041,"name":"BitcoinZ","symbol":"BTCZ","website_slug":"bitcoinz","rank":634,"circulating_supply":2260387717,"total_supply":2260387717,"max_supply":21000000000,"quotes":{"USD":{"price":0.00174418,"volume_24h":81861.1,"market_cap":3942523,"percent_change_1h":-0.24,"percent_change_24h":2.85,"percent_change_7d":15.76}},"last_updated":1532328280},"2844":{"id":2844,"name":"Shivom","symbol":"OMX","website_slug":"shivom","rank":635,"circulating_supply":318758997,"total_supply":3000000000,"max_supply":null,"quotes":{"USD":{"price":0.0122971,"volume_24h":441442,"market_cap":3919811,"percent_change_1h":-0.02,"percent_change_24h":6.63,"percent_change_7d":-7.38}},"last_updated":1532328288},"2426":{"id":2426,"name":"ShareX","symbol":"SEXC","website_slug":"sharex","rank":636,"circulating_supply":645515075,"total_supply":1000000000,"max_supply":null,"quotes":{"USD":{"price":0.00603597,"volume_24h":135010,"market_cap":3896310,"percent_change_1h":-0.95,"percent_change_24h":-12.67,"percent_change_7d":-9.61}},"last_updated":1532328280},"2359":{"id":2359,"name":"Polis","symbol":"POLIS","website_slug":"polis","rank":637,"circulating_supply":2965137,"total_supply":2965137,"max_supply":25000000,"quotes":{"USD":{"price":1.30881,"volume_24h":15472.3,"market_cap":3880801,"percent_change_1h":0.72,"percent_change_24h":1.12,"percent_change_7d":2.07}},"last_updated":1532328282},"2356":{"id":2356,"name":"CFun","symbol":"CFUN","website_slug":"cfun","rank":638,"circulating_supply":429429737,"total_supply":900000000,"max_supply":null,"quotes":{"USD":{"price":0.00902833,"volume_24h":245170,"market_cap":3877033,"percent_change_1h":-1.99,"percent_change_24h":-2.28,"percent_change_7d":-1.95}},"last_updated":1532328284},"1841":{"id":1841,"name":"Primalbase Token","symbol":"PBT","website_slug":"primalbase","rank":639,"circulating_supply":1250,"total_supply":1250,"max_supply":1250,"quotes":{"USD":{"price":3082.17,"volume_24h":368991,"market_cap":3852713,"percent_change_1h":0.33,"percent_change_24h":1.65,"percent_change_7d":10.51}},"last_updated":1532328271},"2495":{"id":2495,"name":"Pareto Network","symbol":"PARETO","website_slug":"pareto-network","rank":640,"circulating_supply":248153959,"total_supply":500000000,"max_supply":null,"quotes":{"USD":{"price":0.0154699,"volume_24h":20645.8,"market_cap":3838917,"percent_change_1h":0.62,"percent_change_24h":2.75,"percent_change_7d":1.8}},"last_updated":1532328288},"2500":{"id":2500,"name":"Zilla","symbol":"ZLA","website_slug":"zilla","rank":641,"circulating_supply":38966654,"total_supply":60000000,"max_supply":null,"quotes":{"USD":{"price":0.0984648,"volume_24h":92010.4,"market_cap":3836844,"percent_change_1h":-0.46,"percent_change_24h":5.14,"percent_change_7d":2.73}},"last_updated":1532328283},"2753":{"id":2753,"name":"Colu Local Network","symbol":"CLN","website_slug":"colu-local-network","rank":642,"circulating_supply":112124882,"total_supply":1540701334,"max_supply":null,"quotes":{"USD":{"price":0.0341764,"volume_24h":67809.7,"market_cap":3832025,"percent_change_1h":0.22,"percent_change_24h":0.46,"percent_change_7d":-2.51}},"last_updated":1532328288},"2568":{"id":2568,"name":"JET8","symbol":"J8T","website_slug":"jet8","rank":643,"circulating_supply":452606995,"total_supply":1468857775,"max_supply":null,"quotes":{"USD":{"price":0.00843992,"volume_24h":13750,"market_cap":3819967,"percent_change_1h":0.93,"percent_change_24h":6.34,"percent_change_7d":8.08}},"last_updated":1532328287},"141":{"id":141,"name":"Mintcoin","symbol":"MINT","website_slug":"mintcoin","rank":644,"circulating_supply":24947260808,"total_supply":24947260808,"max_supply":null,"quotes":{"USD":{"price":0.000153065,"volume_24h":1417.69,"market_cap":3818552,"percent_change_1h":0.17,"percent_change_24h":3.52,"percent_change_7d":18.9}},"last_updated":1532328263},"2110":{"id":2110,"name":"Dovu","symbol":"DOVU","website_slug":"dovu","rank":645,"circulating_supply":79745430,"total_supply":963761390,"max_supply":null,"quotes":{"USD":{"price":0.0474217,"volume_24h":1220.07,"market_cap":3781664,"percent_change_1h":5.18,"percent_change_24h":5.57,"percent_change_7d":-15.82}},"last_updated":1532328278},"2334":{"id":2334,"name":"BitClave","symbol":"CAT","website_slug":"bitclave","rank":646,"circulating_supply":501394406,"total_supply":1597746125,"max_supply":null,"quotes":{"USD":{"price":0.00753552,"volume_24h":7707.82,"market_cap":3778268,"percent_change_1h":-0.48,"percent_change_24h":-2.07,"percent_change_7d":-12.16}},"last_updated":1532328277},"1531":{"id":1531,"name":"Global Cryptocurrency","symbol":"GCC","website_slug":"global-cryptocurrency","rank":647,"circulating_supply":1116702170,"total_supply":1506948738,"max_supply":2400000000,"quotes":{"USD":{"price":0.00336591,"volume_24h":12087.2,"market_cap":3758719,"percent_change_1h":0.93,"percent_change_24h":3.67,"percent_change_7d":8}},"last_updated":1532328274},"1638":{"id":1638,"name":"WeTrust","symbol":"TRST","website_slug":"trust","rank":648,"circulating_supply":92147500,"total_supply":100000000,"max_supply":100000000,"quotes":{"USD":{"price":0.0405215,"volume_24h":89511.1,"market_cap":3733955,"percent_change_1h":0.02,"percent_change_24h":1.7,"percent_change_7d":5.68}},"last_updated":1532328271},"2030":{"id":2030,"name":"REAL","symbol":"REAL","website_slug":"real","rank":649,"circulating_supply":10055817,"total_supply":19717288,"max_supply":null,"quotes":{"USD":{"price":0.36908,"volume_24h":2680.91,"market_cap":3711401,"percent_change_1h":-0.11,"percent_change_24h":32.86,"percent_change_7d":29.03}},"last_updated":1532328281},"2258":{"id":2258,"name":"Snovio","symbol":"SNOV","website_slug":"snovio","rank":650,"circulating_supply":404980448,"total_supply":651129644,"max_supply":null,"quotes":{"USD":{"price":0.00913254,"volume_24h":155765,"market_cap":3698500,"percent_change_1h":2.82,"percent_change_24h":2.22,"percent_change_7d":0.79}},"last_updated":1532328281},"788":{"id":788,"name":"Circuits of Value","symbol":"COVAL","website_slug":"circuits-of-value","rank":651,"circulating_supply":1000000000,"total_supply":1200000000,"max_supply":null,"quotes":{"USD":{"price":0.00367316,"volume_24h":4142.29,"market_cap":3673160,"percent_change_1h":0.17,"percent_change_24h":-0.59,"percent_change_7d":10.35}},"last_updated":1532328266},"2695":{"id":2695,"name":"VeriME","symbol":"VME","website_slug":"verime","rank":652,"circulating_supply":163380890,"total_supply":400000000,"max_supply":null,"quotes":{"USD":{"price":0.0222571,"volume_24h":258247,"market_cap":3636385,"percent_change_1h":0.56,"percent_change_24h":-5.21,"percent_change_7d":17.25}},"last_updated":1532328286},"2518":{"id":2518,"name":"LOCIcoin","symbol":"LOCI","website_slug":"locicoin","rank":653,"circulating_supply":36518110,"total_supply":100000000,"max_supply":null,"quotes":{"USD":{"price":0.0990803,"volume_24h":10213.4,"market_cap":3618225,"percent_change_1h":0.14,"percent_change_24h":0.9,"percent_change_7d":91.04}},"last_updated":1532328283},"2402":{"id":2402,"name":"Sense","symbol":"SENSE","website_slug":"sense","rank":654,"circulating_supply":179111869,"total_supply":663636366,"max_supply":null,"quotes":{"USD":{"price":0.0201413,"volume_24h":1023.23,"market_cap":3607546,"percent_change_1h":0.64,"percent_change_24h":-0.89,"percent_change_7d":2.75}},"last_updated":1532328284},"916":{"id":916,"name":"MedicCoin","symbol":"MEDIC","website_slug":"mediccoin","rank":655,"circulating_supply":197304561,"total_supply":197304998,"max_supply":null,"quotes":{"USD":{"price":0.0181653,"volume_24h":3864.36,"market_cap":3584097,"percent_change_1h":0.01,"percent_change_24h":-8.22,"percent_change_7d":-26.65}},"last_updated":1532328271},"2478":{"id":2478,"name":"CoinFi","symbol":"COFI","website_slug":"coinfi","rank":656,"circulating_supply":173547535,"total_supply":300000000,"max_supply":null,"quotes":{"USD":{"price":0.0204636,"volume_24h":83472.5,"market_cap":3551407,"percent_change_1h":-0.2,"percent_change_24h":4.16,"percent_change_7d":1.68}},"last_updated":1532328287},"2501":{"id":2501,"name":"adbank","symbol":"ADB","website_slug":"adbank","rank":657,"circulating_supply":500953700,"total_supply":1000000000,"max_supply":null,"quotes":{"USD":{"price":0.00707379,"volume_24h":76843.9,"market_cap":3543641,"percent_change_1h":-0.06,"percent_change_24h":1.95,"percent_change_7d":-2.98}},"last_updated":1532328283},"2601":{"id":2601,"name":"1World","symbol":"1WO","website_slug":"1world","rank":658,"circulating_supply":20686551,"total_supply":37219453,"max_supply":null,"quotes":{"USD":{"price":0.170423,"volume_24h":69220.2,"market_cap":3525464,"percent_change_1h":0.03,"percent_change_24h":-0.2,"percent_change_7d":0.38}},"last_updated":1532328286},"1771":{"id":1771,"name":"DAO.Casino","symbol":"BET","website_slug":"dao-casino","rank":659,"circulating_supply":167270821,"total_supply":167270821,"max_supply":null,"quotes":{"USD":{"price":0.0210236,"volume_24h":677.229,"market_cap":3516635,"percent_change_1h":-0.11,"percent_change_24h":5.6,"percent_change_7d":-5.26}},"last_updated":1532328274},"2557":{"id":2557,"name":"Bee Token","symbol":"BEE","website_slug":"bee-token","rank":660,"circulating_supply":169595585,"total_supply":500000000,"max_supply":null,"quotes":{"USD":{"price":0.020592,"volume_24h":2068.9,"market_cap":3492312,"percent_change_1h":-0.5,"percent_change_24h":0.92,"percent_change_7d":-3.91}},"last_updated":1532328284},"293":{"id":293,"name":"Bitcoin Plus","symbol":"XBC","website_slug":"bitcoin-plus","rank":661,"circulating_supply":112080,"total_supply":112080,"max_supply":1000000,"quotes":{"USD":{"price":30.8476,"volume_24h":5300.19,"market_cap":3457407,"percent_change_1h":1.06,"percent_change_24h":2.5,"percent_change_7d":22.95}},"last_updated":1532328265},"2776":{"id":2776,"name":"Travala","symbol":"AVA","website_slug":"travala","rank":662,"circulating_supply":27226584,"total_supply":61571086,"max_supply":null,"quotes":{"USD":{"price":0.126416,"volume_24h":6233.56,"market_cap":3441876,"percent_change_1h":-0.49,"percent_change_24h":-0.78,"percent_change_7d":-0.33}},"last_updated":1532328288},"1304":{"id":1304,"name":"Syndicate","symbol":"SYNX","website_slug":"syndicate","rank":663,"circulating_supply":19531650,"total_supply":19531650,"max_supply":null,"quotes":{"USD":{"price":0.174968,"volume_24h":36761.9,"market_cap":3417414,"percent_change_1h":1.1,"percent_change_24h":2.22,"percent_change_7d":13.56}},"last_updated":1532328268},"2295":{"id":2295,"name":"Starbase","symbol":"STAR","website_slug":"starbase","rank":664,"circulating_supply":187500000,"total_supply":1000000000,"max_supply":null,"quotes":{"USD":{"price":0.0182204,"volume_24h":3045.36,"market_cap":3416325,"percent_change_1h":18.3,"percent_change_24h":31.18,"percent_change_7d":108.34}},"last_updated":1532328281},"2761":{"id":2761,"name":"Local World Forwarders","symbol":"LWF","website_slug":"local-world-forwarders","rank":665,"circulating_supply":95086007,"total_supply":106232275,"max_supply":null,"quotes":{"USD":{"price":0.0358133,"volume_24h":649.939,"market_cap":3405344,"percent_change_1h":0.17,"percent_change_24h":1.24,"percent_change_7d":21.06}},"last_updated":1532328289},"374":{"id":374,"name":"ArtByte","symbol":"ABY","website_slug":"artbyte","rank":666,"circulating_supply":792537250,"total_supply":792537250,"max_supply":null,"quotes":{"USD":{"price":0.00429631,"volume_24h":3894.11,"market_cap":3404986,"percent_change_1h":-0.97,"percent_change_24h":2.55,"percent_change_7d":16.09}},"last_updated":1532328264},"2207":{"id":2207,"name":"DigiPulse","symbol":"DGPT","website_slug":"digipulse","rank":667,"circulating_supply":2262814,"total_supply":5420576,"max_supply":null,"quotes":{"USD":{"price":1.50184,"volume_24h":23990.3,"market_cap":3398385,"percent_change_1h":-3.61,"percent_change_24h":-0.46,"percent_change_7d":283.59}},"last_updated":1532328281},"2650":{"id":2650,"name":"CommerceBlock","symbol":"CBT","website_slug":"commerceblock","rank":668,"circulating_supply":173256686,"total_supply":743256686,"max_supply":null,"quotes":{"USD":{"price":0.0194033,"volume_24h":7518.4,"market_cap":3361751,"percent_change_1h":3.08,"percent_change_24h":-25.49,"percent_change_7d":0.02}},"last_updated":1532328286},"151":{"id":151,"name":"Pesetacoin","symbol":"PTC","website_slug":"pesetacoin","rank":669,"circulating_supply":134900694,"total_supply":134900694,"max_supply":null,"quotes":{"USD":{"price":0.0247304,"volume_24h":4539.55,"market_cap":3336148,"percent_change_1h":-0.13,"percent_change_24h":-3.23,"percent_change_7d":15.39}},"last_updated":1532328265},"2040":{"id":2040,"name":"ALIS","symbol":"ALIS","website_slug":"alis","rank":670,"circulating_supply":38805314,"total_supply":75209200,"max_supply":null,"quotes":{"USD":{"price":0.0851129,"volume_24h":6619.32,"market_cap":3302833,"percent_change_1h":0.17,"percent_change_24h":2.23,"percent_change_7d":15.72}},"last_updated":1532328278},"2610":{"id":2610,"name":"Peculium","symbol":"PCL","website_slug":"peculium","rank":671,"circulating_supply":951376903,"total_supply":7672701535,"max_supply":null,"quotes":{"USD":{"price":0.00346896,"volume_24h":252358,"market_cap":3300288,"percent_change_1h":-0.24,"percent_change_24h":-1.11,"percent_change_7d":6.17}},"last_updated":1532328284},"1504":{"id":1504,"name":"InflationCoin","symbol":"IFLT","website_slug":"inflationcoin","rank":672,"circulating_supply":44790092020,"total_supply":44790092020,"max_supply":null,"quotes":{"USD":{"price":7.36627e-5,"volume_24h":8239.08,"market_cap":3299359,"percent_change_1h":-44.02,"percent_change_24h":-64,"percent_change_7d":430.74}},"last_updated":1532328276},"2076":{"id":2076,"name":"Blue Protocol","symbol":"BLUE","website_slug":"ethereum-blue","rank":673,"circulating_supply":36645278,"total_supply":42000000,"max_supply":42000000,"quotes":{"USD":{"price":0.0896007,"volume_24h":1574.55,"market_cap":3283443,"percent_change_1h":0.09,"percent_change_24h":-1.75,"percent_change_7d":33.37}},"last_updated":1532328280},"2069":{"id":2069,"name":"Open Trading Network","symbol":"OTN","website_slug":"open-trading-network","rank":674,"circulating_supply":1940632,"total_supply":82630002,"max_supply":100000000,"quotes":{"USD":{"price":1.6472,"volume_24h":39299.3,"market_cap":3196609,"percent_change_1h":0.22,"percent_change_24h":4.35,"percent_change_7d":52.67}},"last_updated":1532328274},"1969":{"id":1969,"name":"Sociall","symbol":"SCL","website_slug":"sociall","rank":675,"circulating_supply":16714020,"total_supply":16714020,"max_supply":16714020,"quotes":{"USD":{"price":0.188791,"volume_24h":545.252,"market_cap":3155456,"percent_change_1h":0.72,"percent_change_24h":12.31,"percent_change_7d":29.36}},"last_updated":1532328280},"1588":{"id":1588,"name":"Tokes","symbol":"TKS","website_slug":"tokes","rank":676,"circulating_supply":3383851,"total_supply":50000000,"max_supply":null,"quotes":{"USD":{"price":0.923493,"volume_24h":7435.79,"market_cap":3124963,"percent_change_1h":0.17,"percent_change_24h":0.76,"percent_change_7d":22.36}},"last_updated":1532328274},"2686":{"id":2686,"name":"Lendingblock","symbol":"LND","website_slug":"lendingblock","rank":677,"circulating_supply":594772963,"total_supply":1000000000,"max_supply":null,"quotes":{"USD":{"price":0.00522258,"volume_24h":34451.8,"market_cap":3106249,"percent_change_1h":5.27,"percent_change_24h":0.01,"percent_change_7d":-13.96}},"last_updated":1532328289},"1931":{"id":1931,"name":"Opus","symbol":"OPT","website_slug":"opus","rank":678,"circulating_supply":140080549,"total_supply":249308531,"max_supply":249308531,"quotes":{"USD":{"price":0.0221695,"volume_24h":4023.89,"market_cap":3105516,"percent_change_1h":3.22,"percent_change_24h":9.71,"percent_change_7d":36.19}},"last_updated":1532328280},"2674":{"id":2674,"name":"Masari","symbol":"MSR","website_slug":"masari","rank":679,"circulating_supply":6514466,"total_supply":6514466,"max_supply":18500000,"quotes":{"USD":{"price":0.475415,"volume_24h":4544.39,"market_cap":3097075,"percent_change_1h":0.31,"percent_change_24h":-2.5,"percent_change_7d":-7.72}},"last_updated":1532328286},"2562":{"id":2562,"name":"Education Ecosystem","symbol":"LEDU","website_slug":"education-ecosystem","rank":680,"circulating_supply":217789857,"total_supply":362983094,"max_supply":null,"quotes":{"USD":{"price":0.0141244,"volume_24h":256971,"market_cap":3076151,"percent_change_1h":-6.51,"percent_change_24h":-21.16,"percent_change_7d":44.55}},"last_updated":1532328282},"148":{"id":148,"name":"Auroracoin","symbol":"AUR","website_slug":"auroracoin","rank":681,"circulating_supply":8658139,"total_supply":8658139,"max_supply":null,"quotes":{"USD":{"price":0.353082,"volume_24h":2666.48,"market_cap":3057033,"percent_change_1h":0.03,"percent_change_24h":5.42,"percent_change_7d":-2.89}},"last_updated":1532328263},"2582":{"id":2582,"name":"LALA World","symbol":"LALA","website_slug":"lala-world","rank":682,"circulating_supply":189647051,"total_supply":250000000,"max_supply":null,"quotes":{"USD":{"price":0.0158846,"volume_24h":22735.3,"market_cap":3012468,"percent_change_1h":0.42,"percent_change_24h":1.37,"percent_change_7d":-15.33}},"last_updated":1532328289},"25":{"id":25,"name":"GoldCoin","symbol":"GLD","website_slug":"goldcoin","rank":683,"circulating_supply":41162408,"total_supply":41162408,"max_supply":72245700,"quotes":{"USD":{"price":0.0727896,"volume_24h":7463.04,"market_cap":2996195,"percent_change_1h":1.02,"percent_change_24h":-5.77,"percent_change_7d":14.92}},"last_updated":1532328254},"2244":{"id":2244,"name":"Payfair","symbol":"PFR","website_slug":"payfair","rank":684,"circulating_supply":88999687,"total_supply":88999687,"max_supply":null,"quotes":{"USD":{"price":0.0336377,"volume_24h":1804.15,"market_cap":2993745,"percent_change_1h":-2.17,"percent_change_24h":-4.56,"percent_change_7d":-11.14}},"last_updated":1532328281},"594":{"id":594,"name":"BunnyCoin","symbol":"BUN","website_slug":"bunnycoin","rank":685,"circulating_supply":103036607564,"total_supply":103036607564,"max_supply":null,"quotes":{"USD":{"price":2.90035e-5,"volume_24h":3912.85,"market_cap":2988422,"percent_change_1h":1.16,"percent_change_24h":21.59,"percent_change_7d":2.84}},"last_updated":1532328267},"2464":{"id":2464,"name":"Devery","symbol":"EVE","website_slug":"devery","rank":686,"circulating_supply":62918410,"total_supply":100000000,"max_supply":null,"quotes":{"USD":{"price":0.0474222,"volume_24h":160730,"market_cap":2983729,"percent_change_1h":-0.18,"percent_change_24h":-1.53,"percent_change_7d":-4.64}},"last_updated":1532328287},"2419":{"id":2419,"name":"Profile Utility Token","symbol":"PUT","website_slug":"profile-utility-token","rank":687,"circulating_supply":45289804,"total_supply":100000000,"max_supply":null,"quotes":{"USD":{"price":0.0654832,"volume_24h":594432,"market_cap":2965721,"percent_change_1h":-1.99,"percent_change_24h":-4.71,"percent_change_7d":-10.31}},"last_updated":1532328280},"2549":{"id":2549,"name":"Ink Protocol","symbol":"XNK","website_slug":"ink-protocol","rank":688,"circulating_supply":176630334,"total_supply":500000000,"max_supply":null,"quotes":{"USD":{"price":0.0167878,"volume_24h":134896,"market_cap":2965235,"percent_change_1h":0.48,"percent_change_24h":0.88,"percent_change_7d":-16.35}},"last_updated":1532328284},"2899":{"id":2899,"name":"Thrive Token","symbol":"THRT","website_slug":"thrive-token","rank":689,"circulating_supply":90459837,"total_supply":202027490,"max_supply":null,"quotes":{"USD":{"price":0.0325499,"volume_24h":820388,"market_cap":2944459,"percent_change_1h":-0.03,"percent_change_24h":24.13,"percent_change_7d":22.51}},"last_updated":1532328289},"2445":{"id":2445,"name":"Block Array","symbol":"ARY","website_slug":"block-array","rank":690,"circulating_supply":68430738,"total_supply":88409933,"max_supply":null,"quotes":{"USD":{"price":0.0429535,"volume_24h":2737.89,"market_cap":2939340,"percent_change_1h":-0.06,"percent_change_24h":6.79,"percent_change_7d":6.72}},"last_updated":1532328282},"1252":{"id":1252,"name":"2GIVE","symbol":"2GIVE","website_slug":"2give","rank":691,"circulating_supply":520033685,"total_supply":520033685,"max_supply":null,"quotes":{"USD":{"price":0.00558476,"volume_24h":7174.7,"market_cap":2904263,"percent_change_1h":1.45,"percent_change_24h":-1.13,"percent_change_7d":6.95}},"last_updated":1532328272},"2190":{"id":2190,"name":"Astro","symbol":"ASTRO","website_slug":"astro","rank":692,"circulating_supply":3313833,"total_supply":6999999,"max_supply":null,"quotes":{"USD":{"price":0.874118,"volume_24h":528.39,"market_cap":2896681,"percent_change_1h":-0.11,"percent_change_24h":null,"percent_change_7d":-20.85}},"last_updated":1532328275},"1902":{"id":1902,"name":"MyBit Token","symbol":"MYB","website_slug":"mybit-token","rank":693,"circulating_supply":70639871,"total_supply":180000000,"max_supply":null,"quotes":{"USD":{"price":0.0409655,"volume_24h":47766.7,"market_cap":2893798,"percent_change_1h":-0.09,"percent_change_24h":-5.87,"percent_change_7d":24.34}},"last_updated":1532328277},"400":{"id":400,"name":"Kore","symbol":"KORE","website_slug":"korecoin","rank":694,"circulating_supply":2022465,"total_supply":2022465,"max_supply":12000000,"quotes":{"USD":{"price":1.42396,"volume_24h":37908.2,"market_cap":2879909,"percent_change_1h":-2.52,"percent_change_24h":-0.6,"percent_change_7d":2.31}},"last_updated":1532328264},"2288":{"id":2288,"name":"Worldcore","symbol":"WRC","website_slug":"worldcore","rank":695,"circulating_supply":178103291,"total_supply":245209299,"max_supply":null,"quotes":{"USD":{"price":0.0160588,"volume_24h":11370.9,"market_cap":2860125,"percent_change_1h":0.47,"percent_change_24h":14.77,"percent_change_7d":24.77}},"last_updated":1532328280},"2580":{"id":2580,"name":"Leadcoin","symbol":"LDC","website_slug":"leadcoin","rank":696,"circulating_supply":784399592,"total_supply":2627412706,"max_supply":null,"quotes":{"USD":{"price":0.00361963,"volume_24h":439320,"market_cap":2839236,"percent_change_1h":-0.02,"percent_change_24h":0.76,"percent_change_7d":4.61}},"last_updated":1532328286},"1032":{"id":1032,"name":"TransferCoin","symbol":"TX","website_slug":"transfercoin","rank":697,"circulating_supply":6560044,"total_supply":6560044,"max_supply":null,"quotes":{"USD":{"price":0.432789,"volume_24h":75820.2,"market_cap":2839115,"percent_change_1h":0.16,"percent_change_24h":-0.61,"percent_change_7d":30.87}},"last_updated":1532328266},"2384":{"id":2384,"name":"Vezt","symbol":"VZT","website_slug":"vezt","rank":698,"circulating_supply":57984917,"total_supply":125000000,"max_supply":null,"quotes":{"USD":{"price":0.0486933,"volume_24h":1678.68,"market_cap":2823477,"percent_change_1h":-0.01,"percent_change_24h":7,"percent_change_7d":16.02}},"last_updated":1532328279},"2619":{"id":2619,"name":"BitStation","symbol":"BSTN","website_slug":"bitstation","rank":699,"circulating_supply":3467018936,"total_supply":12000000000,"max_supply":null,"quotes":{"USD":{"price":0.000813498,"volume_24h":54932.1,"market_cap":2820413,"percent_change_1h":-0.92,"percent_change_24h":6.51,"percent_change_7d":-0.47}},"last_updated":1532328285}},"metadata":{"timestamp":1532327878,"num_cryptocurrencies":1656,"error":null}}}