{"data":{"data":{"2861":{"id":2861,"name":"GoChain","symbol":"GO","website_slug":"gochain","rank":200,"circulating_supply":499613958,"total_supply":1008251425,"max_supply":null,"quotes":{"USD":{"price":0.0703023,"volume_24h":906433,"market_cap":35124010,"percent_change_1h":-2.11,"percent_change_24h":-2.54,"percent_change_7d":-0.39}},"last_updated":1532328285},"1595":{"id":1595,"name":"Soarcoin","symbol":"SOAR","website_slug":"soarcoin","rank":201,"circulating_supply":1076141972,"total_supply":5000000000,"max_supply":5000000000,"quotes":{"USD":{"price":0.0325993,"volume_24h":56549.6,"market_cap":35081475,"percent_change_1h":0.17,"percent_change_24h":6.68,"percent_change_7d":38.49}},"last_updated":1532328271},"2306":{"id":2306,"name":"Bread","symbol":"BRD","website_slug":"bread","rank":202,"circulating_supply":88733978,"total_supply":88862718,"max_supply":null,"quotes":{"USD":{"price":0.391842,"volume_24h":1121990,"market_cap":34769699,"percent_change_1h":0.19,"percent_change_24h":1.81,"percent_change_7d":-5.13}},"last_updated":1532328279},"2398":{"id":2398,"name":"Selfkey","symbol":"KEY","website_slug":"selfkey","rank":203,"circulating_supply":2428461491,"total_supply":5999999954,"max_supply":null,"quotes":{"USD":{"price":0.0141551,"volume_24h":24600300,"market_cap":34375115,"percent_change_1h":2,"percent_change_24h":21.34,"percent_change_7d":13.15}},"last_updated":1532328282},"1788":{"id":1788,"name":"Metal","symbol":"MTL","website_slug":"metal","rank":204,"circulating_supply":25240243,"total_supply":66588888,"max_supply":null,"quotes":{"USD":{"price":1.35595,"volume_24h":1831300,"market_cap":34224508,"percent_change_1h":-0.41,"percent_change_24h":3.25,"percent_change_7d":7.17}},"last_updated":1532328278},"67":{"id":67,"name":"Unobtanium","symbol":"UNO","website_slug":"unobtanium","rank":205,"circulating_supply":198972,"total_supply":198972,"max_supply":null,"quotes":{"USD":{"price":170.278,"volume_24h":111366,"market_cap":33880491,"percent_change_1h":2.39,"percent_change_24h":14.97,"percent_change_7d":14.94}},"last_updated":1532328263},"2394":{"id":2394,"name":"Telcoin","symbol":"TEL","website_slug":"telcoin","rank":206,"circulating_supply":31340395144,"total_supply":100000000000,"max_supply":null,"quotes":{"USD":{"price":0.00107703,"volume_24h":69863.6,"market_cap":33754546,"percent_change_1h":-0.69,"percent_change_24h":0.51,"percent_change_7d":3.38}},"last_updated":1532328281},"2541":{"id":2541,"name":"Storiqa","symbol":"STQ","website_slug":"storiqa","rank":207,"circulating_supply":8031201219,"total_supply":11287544272,"max_supply":null,"quotes":{"USD":{"price":0.00420204,"volume_24h":499595,"market_cap":33747429,"percent_change_1h":0.14,"percent_change_24h":-0.04,"percent_change_7d":-7.86}},"last_updated":1532328284},"2458":{"id":2458,"name":"Odyssey","symbol":"OCN","website_slug":"odyssey","rank":208,"circulating_supply":4750000000,"total_supply":10000000000,"max_supply":null,"quotes":{"USD":{"price":0.00704541,"volume_24h":7884410,"market_cap":33465698,"percent_change_1h":0.55,"percent_change_24h":3.04,"percent_change_7d":8.03}},"last_updated":1532328284},"2373":{"id":2373,"name":"Trade Token","symbol":"TIO","website_slug":"trade-token","rank":209,"circulating_supply":89921436,"total_supply":223534823,"max_supply":null,"quotes":{"USD":{"price":0.371792,"volume_24h":107959,"market_cap":33432071,"percent_change_1h":-0.87,"percent_change_24h":3.21,"percent_change_7d":2.17}},"last_updated":1532328284},"2576":{"id":2576,"name":"Tokenomy","symbol":"TEN","website_slug":"tokenomy","rank":210,"circulating_supply":146000000,"total_supply":200000000,"max_supply":null,"quotes":{"USD":{"price":0.226077,"volume_24h":1197600,"market_cap":33007242,"percent_change_1h":-0.48,"percent_change_24h":-1.26,"percent_change_7d":2.25}},"last_updated":1532328283},"1596":{"id":1596,"name":"Edgeless","symbol":"EDG","website_slug":"edgeless","rank":211,"circulating_supply":95639612,"total_supply":132046997,"max_supply":null,"quotes":{"USD":{"price":0.344918,"volume_24h":426069,"market_cap":32987824,"percent_change_1h":0.24,"percent_change_24h":2.06,"percent_change_7d":9.75}},"last_updated":1532328271},"2896":{"id":2896,"name":"Mainframe","symbol":"MFT","website_slug":"mainframe","rank":212,"circulating_supply":2163833975,"total_supply":10000000000,"max_supply":null,"quotes":{"USD":{"price":0.0149867,"volume_24h":6222490,"market_cap":32428731,"percent_change_1h":1.2,"percent_change_24h":1.17,"percent_change_7d":-4.1}},"last_updated":1532328287},"1712":{"id":1712,"name":"Quantum Resistant Ledger","symbol":"QRL","website_slug":"quantum-resistant-ledger","rank":213,"circulating_supply":52000000,"total_supply":65000000,"max_supply":105000000,"quotes":{"USD":{"price":0.620379,"volume_24h":2562000,"market_cap":32259708,"percent_change_1h":-0.62,"percent_change_24h":-18.37,"percent_change_7d":54.46}},"last_updated":1532328272},"576":{"id":576,"name":"GameCredits","symbol":"GAME","website_slug":"gamecredits","rank":214,"circulating_supply":64355352,"total_supply":64355352,"max_supply":84000000,"quotes":{"USD":{"price":0.498509,"volume_24h":157824,"market_cap":32081722,"percent_change_1h":-0.59,"percent_change_24h":-1.8,"percent_change_7d":12.9}},"last_updated":1532328269},"723":{"id":723,"name":"BitBay","symbol":"BAY","website_slug":"bitbay","rank":215,"circulating_supply":1012146906,"total_supply":1012146906,"max_supply":null,"quotes":{"USD":{"price":0.0315062,"volume_24h":38116.8,"market_cap":31888903,"percent_change_1h":-1.04,"percent_change_24h":4.6,"percent_change_7d":14.31}},"last_updated":1532328268},"2644":{"id":2644,"name":"eosDAC","symbol":"EOSDAC","website_slug":"eosdac","rank":216,"circulating_supply":660755177,"total_supply":1200000000,"max_supply":null,"quotes":{"USD":{"price":0.0467595,"volume_24h":125394,"market_cap":30896582,"percent_change_1h":-0.82,"percent_change_24h":-5.99,"percent_change_7d":-15.72}},"last_updated":1532328283},"2473":{"id":2473,"name":"All Sports","symbol":"SOC","website_slug":"all-sports","rank":217,"circulating_supply":883089416,"total_supply":1500000000,"max_supply":null,"quotes":{"USD":{"price":0.034915,"volume_24h":2560940,"market_cap":30833067,"percent_change_1h":-0.69,"percent_change_24h":9.91,"percent_change_7d":-17.15}},"last_updated":1532328286},"2732":{"id":2732,"name":"Aston","symbol":"ATX","website_slug":"aston","rank":218,"circulating_supply":824000000,"total_supply":1000000000,"max_supply":null,"quotes":{"USD":{"price":0.036452,"volume_24h":58062.7,"market_cap":30036448,"percent_change_1h":7.56,"percent_change_24h":3.11,"percent_change_7d":-10.7}},"last_updated":1532328287},"2550":{"id":2550,"name":"Rock","symbol":"RKT","website_slug":"rock","rank":219,"circulating_supply":393051949,"total_supply":900000000,"max_supply":null,"quotes":{"USD":{"price":0.07557,"volume_24h":69781.7,"market_cap":29702936,"percent_change_1h":0.04,"percent_change_24h":5.58,"percent_change_7d":9.93}},"last_updated":1532328284},"2239":{"id":2239,"name":"ETHLend","symbol":"LEND","website_slug":"ethlend","rank":220,"circulating_supply":1098246878,"total_supply":1299999942,"max_supply":null,"quotes":{"USD":{"price":0.0270134,"volume_24h":296626,"market_cap":29667382,"percent_change_1h":0.17,"percent_change_24h":0.42,"percent_change_7d":3.7}},"last_updated":1532328279},"2552":{"id":2552,"name":"IHT Real Estate Protocol","symbol":"IHT","website_slug":"iht-real-estate-protocol","rank":221,"circulating_supply":507320393,"total_supply":1000000000,"max_supply":null,"quotes":{"USD":{"price":0.0578537,"volume_24h":5845940,"market_cap":29350362,"percent_change_1h":-3,"percent_change_24h":-6,"percent_change_7d":-6.3}},"last_updated":1532328287},"2112":{"id":2112,"name":"Red Pulse","symbol":"RPX","website_slug":"red-pulse","rank":222,"circulating_supply":809366304,"total_supply":1358371250,"max_supply":null,"quotes":{"USD":{"price":0.0362327,"volume_24h":375148,"market_cap":29325526,"percent_change_1h":-1.02,"percent_change_24h":-0.56,"percent_change_7d":5.17}},"last_updated":1532328278},"2742":{"id":2742,"name":"Sakura Bloom","symbol":"SKB","website_slug":"sakura-bloom","rank":223,"circulating_supply":2582965294,"total_supply":6000000000,"max_supply":null,"quotes":{"USD":{"price":0.0112963,"volume_24h":124075,"market_cap":29177951,"percent_change_1h":0.86,"percent_change_24h":-4.94,"percent_change_7d":-7.49}},"last_updated":1532328285},"1654":{"id":1654,"name":"Bitcore","symbol":"BTX","website_slug":"bitcore","rank":224,"circulating_supply":15631064,"total_supply":17085291,"max_supply":21000000,"quotes":{"USD":{"price":1.84866,"volume_24h":357946,"market_cap":28896522,"percent_change_1h":-0.15,"percent_change_24h":-0.83,"percent_change_7d":13.32}},"last_updated":1532328274},"2835":{"id":2835,"name":"Endor Protocol","symbol":"EDR","website_slug":"endor-protocol","rank":225,"circulating_supply":525844682,"total_supply":1469247736,"max_supply":null,"quotes":{"USD":{"price":0.0544316,"volume_24h":1851830,"market_cap":28622567,"percent_change_1h":-1.55,"percent_change_24h":-3.1,"percent_change_7d":8.76}},"last_updated":1532328288},"1768":{"id":1768,"name":"AdEx","symbol":"ADX","website_slug":"adx-net","rank":226,"circulating_supply":73430701,"total_supply":100000000,"max_supply":100000000,"quotes":{"USD":{"price":0.389425,"volume_24h":731991,"market_cap":28595751,"percent_change_1h":-0.15,"percent_change_24h":2.12,"percent_change_7d":5.16}},"last_updated":1532328275},"2139":{"id":2139,"name":"MinexCoin","symbol":"MNX","website_slug":"minexcoin","rank":227,"circulating_supply":3987863,"total_supply":5929943,"max_supply":19000000,"quotes":{"USD":{"price":7.16957,"volume_24h":67810.5,"market_cap":28591261,"percent_change_1h":0.44,"percent_change_24h":6.37,"percent_change_7d":13.73}},"last_updated":1532328280},"470":{"id":470,"name":"Viacoin","symbol":"VIA","website_slug":"viacoin","rank":228,"circulating_supply":23071680,"total_supply":23071680,"max_supply":23176392,"quotes":{"USD":{"price":1.23655,"volume_24h":511806,"market_cap":28529286,"percent_change_1h":-0.08,"percent_change_24h":0.31,"percent_change_7d":13.26}},"last_updated":1532328267},"201":{"id":201,"name":"Einsteinium","symbol":"EMC2","website_slug":"einsteinium","rank":229,"circulating_supply":217301049,"total_supply":217301049,"max_supply":null,"quotes":{"USD":{"price":0.130304,"volume_24h":466579,"market_cap":28315196,"percent_change_1h":-0.28,"percent_change_24h":-1.42,"percent_change_7d":6.73}},"last_updated":1532328264},"2767":{"id":2767,"name":"APIS","symbol":"APIS","website_slug":"apis","rank":230,"circulating_supply":4416350572,"total_supply":9520000000,"max_supply":null,"quotes":{"USD":{"price":0.006394,"volume_24h":26711600,"market_cap":28238146,"percent_change_1h":-0.01,"percent_change_24h":6.32,"percent_change_7d":43.24}},"last_updated":1532328286},"2538":{"id":2538,"name":"Nectar","symbol":"NEC","website_slug":"nectar","rank":231,"circulating_supply":82353022,"total_supply":1007949847,"max_supply":null,"quotes":{"USD":{"price":0.340919,"volume_24h":27486.2,"market_cap":28075710,"percent_change_1h":-0.08,"percent_change_24h":5.33,"percent_change_7d":-0.31}},"last_updated":1532328285},"2600":{"id":2600,"name":"LGO Exchange","symbol":"LGO","website_slug":"legolas-exchange","rank":232,"circulating_supply":120324679,"total_supply":217698062,"max_supply":null,"quotes":{"USD":{"price":0.233259,"volume_24h":3922.5,"market_cap":28066814,"percent_change_1h":0.59,"percent_change_24h":7.67,"percent_change_7d":-1.15}},"last_updated":1532328286},"2777":{"id":2777,"name":"IoTeX","symbol":"IOTX","website_slug":"iotex","rank":233,"circulating_supply":1141040005,"total_supply":10000000000,"max_supply":null,"quotes":{"USD":{"price":0.0245576,"volume_24h":1731880,"market_cap":28021204,"percent_change_1h":-0.01,"percent_change_24h":2.75,"percent_change_7d":-0.45}},"last_updated":1532328288},"2251":{"id":2251,"name":"IoT Chain","symbol":"ITC","website_slug":"iot-chain","rank":234,"circulating_supply":60562242,"total_supply":100000000,"max_supply":null,"quotes":{"USD":{"price":0.462294,"volume_24h":2521120,"market_cap":27997561,"percent_change_1h":0.48,"percent_change_24h":3.25,"percent_change_7d":9.43}},"last_updated":1532328282},"2371":{"id":2371,"name":"United Traders Token","symbol":"UTT","website_slug":"uttoken","rank":235,"circulating_supply":37341840,"total_supply":69403131,"max_supply":null,"quotes":{"USD":{"price":0.748461,"volume_24h":9074.13,"market_cap":27948911,"percent_change_1h":-0.03,"percent_change_24h":11.94,"percent_change_7d":88.37}},"last_updated":1532328282},"2556":{"id":2556,"name":"Credits","symbol":"CS","website_slug":"credits","rank":236,"circulating_supply":138268126,"total_supply":249471071,"max_supply":null,"quotes":{"USD":{"price":0.201503,"volume_24h":1553510,"market_cap":27861442,"percent_change_1h":-7.86,"percent_change_24h":-7.8,"percent_change_7d":-31.61}},"last_updated":1532328285},"2898":{"id":2898,"name":"GoNetwork","symbol":"GOT","website_slug":"gonetwork","rank":237,"circulating_supply":50645588,"total_supply":100000000,"max_supply":null,"quotes":{"USD":{"price":0.549147,"volume_24h":3518690,"market_cap":27811873,"percent_change_1h":-0.08,"percent_change_24h":0.11,"percent_change_7d":-23.43}},"last_updated":1532328288},"2057":{"id":2057,"name":"Eidoo","symbol":"EDO","website_slug":"eidoo","rank":238,"circulating_supply":29261461,"total_supply":90208328,"max_supply":null,"quotes":{"USD":{"price":0.944971,"volume_24h":1430650,"market_cap":27651232,"percent_change_1h":0.3,"percent_change_24h":4.24,"percent_change_7d":4.28}},"last_updated":1532328278},"2453":{"id":2453,"name":"EDUCare","symbol":"EKT","website_slug":"educare","rank":239,"circulating_supply":450000000,"total_supply":1000000000,"max_supply":null,"quotes":{"USD":{"price":0.0612435,"volume_24h":1916110,"market_cap":27559575,"percent_change_1h":1.11,"percent_change_24h":12.11,"percent_change_7d":-11.82}},"last_updated":1532328288},"42":{"id":42,"name":"Primecoin","symbol":"XPM","website_slug":"primecoin","rank":240,"circulating_supply":24345782,"total_supply":24345782,"max_supply":null,"quotes":{"USD":{"price":1.12956,"volume_24h":298753,"market_cap":27500021,"percent_change_1h":-4.43,"percent_change_24h":-3.43,"percent_change_7d":-9.87}},"last_updated":1532328255},"2482":{"id":2482,"name":"CPChain","symbol":"CPC","website_slug":"cpchain","rank":241,"circulating_supply":376765852,"total_supply":999999999,"max_supply":null,"quotes":{"USD":{"price":0.0722289,"volume_24h":4806070,"market_cap":27213383,"percent_change_1h":0.15,"percent_change_24h":5.59,"percent_change_7d":14.76}},"last_updated":1532328282},"377":{"id":377,"name":"NavCoin","symbol":"NAV","website_slug":"nav-coin","rank":242,"circulating_supply":63093455,"total_supply":63093455,"max_supply":null,"quotes":{"USD":{"price":0.427248,"volume_24h":284668,"market_cap":26956552,"percent_change_1h":0.25,"percent_change_24h":-0.64,"percent_change_7d":6.98}},"last_updated":1532328267},"2162":{"id":2162,"name":"Delphy","symbol":"DPY","website_slug":"delphy","rank":243,"circulating_supply":42622724,"total_supply":100000000,"max_supply":null,"quotes":{"USD":{"price":0.630466,"volume_24h":1253150,"market_cap":26872179,"percent_change_1h":1.05,"percent_change_24h":8.51,"percent_change_7d":19.59}},"last_updated":1532328284},"2467":{"id":2467,"name":"OriginTrail","symbol":"TRAC","website_slug":"origintrail","rank":244,"circulating_supply":268253992,"total_supply":500000000,"max_supply":null,"quotes":{"USD":{"price":0.100134,"volume_24h":101509,"market_cap":26861345,"percent_change_1h":1.93,"percent_change_24h":0.27,"percent_change_7d":1.01}},"last_updated":1532328286},"2840":{"id":2840,"name":"QuarkChain","symbol":"QKC","website_slug":"quarkchain","rank":245,"circulating_supply":357431729,"total_supply":10000000000,"max_supply":null,"quotes":{"USD":{"price":0.0743271,"volume_24h":9942700,"market_cap":26566864,"percent_change_1h":0.16,"percent_change_24h":1.46,"percent_change_7d":0.54}},"last_updated":1532328288},"1159":{"id":1159,"name":"SaluS","symbol":"SLS","website_slug":"salus","rank":246,"circulating_supply":1010771,"total_supply":1010771,"max_supply":null,"quotes":{"USD":{"price":26.1852,"volume_24h":64834.4,"market_cap":26467245,"percent_change_1h":-0.14,"percent_change_24h":0.77,"percent_change_7d":15.92}},"last_updated":1532328268},"573":{"id":573,"name":"Burst","symbol":"BURST","website_slug":"burst","rank":247,"circulating_supply":1966287923,"total_supply":1966287923,"max_supply":2158812800,"quotes":{"USD":{"price":0.0132404,"volume_24h":112700,"market_cap":26034439,"percent_change_1h":-0.67,"percent_change_24h":1.73,"percent_change_7d":0.93}},"last_updated":1532328265},"2209":{"id":2209,"name":"Ink","symbol":"INK","website_slug":"ink","rank":248,"circulating_supply":463910527,"total_supply":1000000000,"max_supply":1000000000,"quotes":{"USD":{"price":0.0550364,"volume_24h":3322910,"market_cap":25531965,"percent_change_1h":-0.88,"percent_change_24h":-7.46,"percent_change_7d":-5.9}},"last_updated":1532328287},"2305":{"id":2305,"name":"NAGA","symbol":"NGC","website_slug":"naga","rank":249,"circulating_supply":57672338,"total_supply":77910266,"max_supply":null,"quotes":{"USD":{"price":0.438769,"volume_24h":239037,"market_cap":25304834,"percent_change_1h":-2.05,"percent_change_24h":0.3,"percent_change_7d":50.07}},"last_updated":1532328279},"2723":{"id":2723,"name":"FuzeX","symbol":"FXT","website_slug":"fuzex","rank":250,"circulating_supply":730346443,"total_supply":1087156610,"max_supply":null,"quotes":{"USD":{"price":0.0344128,"volume_24h":257940,"market_cap":25133266,"percent_change_1h":-0.83,"percent_change_24h":12.43,"percent_change_7d":39.06}},"last_updated":1532328289},"2498":{"id":2498,"name":"Jibrel Network","symbol":"JNT","website_slug":"jibrel-network","rank":251,"circulating_supply":160000000,"total_supply":200000000,"max_supply":null,"quotes":{"USD":{"price":0.157042,"volume_24h":1283200,"market_cap":25126720,"percent_change_1h":-0.58,"percent_change_24h":-4.61,"percent_change_7d":5.89}},"last_updated":1532328283},"2696":{"id":2696,"name":"DAEX","symbol":"DAX","website_slug":"daex","rank":252,"circulating_supply":370300000,"total_supply":2000000000,"max_supply":null,"quotes":{"USD":{"price":0.067487,"volume_24h":4091530,"market_cap":24990436,"percent_change_1h":-2.81,"percent_change_24h":-2.44,"percent_change_7d":-4.07}},"last_updated":1532328287},"2446":{"id":2446,"name":"DATA","symbol":"DTA","website_slug":"data","rank":253,"circulating_supply":4626502186,"total_supply":11500000000,"max_supply":11500000000,"quotes":{"USD":{"price":0.00536454,"volume_24h":954976,"market_cap":24819056,"percent_change_1h":-1.44,"percent_change_24h":-0.17,"percent_change_7d":-11.96}},"last_updated":1532328287},"1711":{"id":1711,"name":"Electra","symbol":"ECA","website_slug":"electra","rank":254,"circulating_supply":26493800974,"total_supply":27360957527,"max_supply":30000000000,"quotes":{"USD":{"price":0.000935586,"volume_24h":140643,"market_cap":24787229,"percent_change_1h":-5.12,"percent_change_24h":-4.98,"percent_change_7d":16.23}},"last_updated":1532328275},"45":{"id":45,"name":"CasinoCoin","symbol":"CSC","website_slug":"casinocoin","rank":255,"circulating_supply":35973085511,"total_supply":39999999905,"max_supply":null,"quotes":{"USD":{"price":0.000688536,"volume_24h":13777.7,"market_cap":24768764,"percent_change_1h":9.78,"percent_change_24h":15.92,"percent_change_7d":52.77}},"last_updated":1532328257},"2554":{"id":2554,"name":"Lympo","symbol":"LYM","website_slug":"lympo","rank":256,"circulating_supply":725940241,"total_supply":999999999,"max_supply":null,"quotes":{"USD":{"price":0.0340824,"volume_24h":3363850,"market_cap":24741786,"percent_change_1h":-0.4,"percent_change_24h":2.79,"percent_change_7d":20.16}},"last_updated":1532328285},"2399":{"id":2399,"name":"Internet Node Token","symbol":"INT","website_slug":"internet-node-token","rank":257,"circulating_supply":295934000,"total_supply":1000000000,"max_supply":null,"quotes":{"USD":{"price":0.0835674,"volume_24h":3088670,"market_cap":24730435,"percent_change_1h":0.72,"percent_change_24h":5.37,"percent_change_7d":-3.85}},"last_updated":1532328280},"1026":{"id":1026,"name":"Aeon","symbol":"AEON","website_slug":"aeon","rank":258,"circulating_supply":15831459,"total_supply":15831459,"max_supply":null,"quotes":{"USD":{"price":1.55473,"volume_24h":19814.9,"market_cap":24613645,"percent_change_1h":-1.43,"percent_change_24h":1.47,"percent_change_7d":13.55}},"last_updated":1532328268},"3":{"id":3,"name":"Namecoin","symbol":"NMC","website_slug":"namecoin","rank":259,"circulating_supply":14736400,"total_supply":14736400,"max_supply":null,"quotes":{"USD":{"price":1.65298,"volume_24h":111168,"market_cap":24358974,"percent_change_1h":-0.18,"percent_change_24h":16.68,"percent_change_7d":4.51}},"last_updated":1532328289},"2881":{"id":2881,"name":"Distributed Credit Chain","symbol":"DCC","website_slug":"distributed-credit-chain","rank":260,"circulating_supply":973089328,"total_supply":3384999548,"max_supply":null,"quotes":{"USD":{"price":0.0247682,"volume_24h":2055170,"market_cap":24101671,"percent_change_1h":5.06,"percent_change_24h":2.52,"percent_change_7d":-10.73}},"last_updated":1532328288},"2296":{"id":2296,"name":"OST","symbol":"OST","website_slug":"ost","rank":261,"circulating_supply":355695066,"total_supply":800000000,"max_supply":null,"quotes":{"USD":{"price":0.0672151,"volume_24h":503887,"market_cap":23908079,"percent_change_1h":-0.69,"percent_change_24h":-0.22,"percent_change_7d":0.57}},"last_updated":1532328281},"2595":{"id":2595,"name":"NANJCOIN","symbol":"NANJ","website_slug":"nanjcoin","rank":262,"circulating_supply":19361889557,"total_supply":30000000000,"max_supply":null,"quotes":{"USD":{"price":0.00123429,"volume_24h":245463,"market_cap":23898187,"percent_change_1h":5.85,"percent_change_24h":-11.05,"percent_change_7d":-1.02}},"last_updated":1532328286},"254":{"id":254,"name":"Gulden","symbol":"NLG","website_slug":"gulden","rank":263,"circulating_supply":401434740,"total_supply":472934740,"max_supply":null,"quotes":{"USD":{"price":0.0595162,"volume_24h":18755.4,"market_cap":23891870,"percent_change_1h":0.11,"percent_change_24h":3.38,"percent_change_7d":5.55}},"last_updated":1532328267},"2539":{"id":2539,"name":"Republic Protocol","symbol":"REN","website_slug":"republic-protocol","rank":264,"circulating_supply":568356499,"total_supply":1000000000,"max_supply":null,"quotes":{"USD":{"price":0.0420038,"volume_24h":999222,"market_cap":23873133,"percent_change_1h":-1.99,"percent_change_24h":0.11,"percent_change_7d":15.29}},"last_updated":1532328284},"2885":{"id":2885,"name":"Egretia","symbol":"EGT","website_slug":"egretia","rank":265,"circulating_supply":2599420370,"total_supply":8000000000,"max_supply":null,"quotes":{"USD":{"price":0.00899949,"volume_24h":900299,"market_cap":23393458,"percent_change_1h":1.13,"percent_change_24h":5.05,"percent_change_7d":-8.57}},"last_updated":1532328288},"2429":{"id":2429,"name":"Mobius","symbol":"MOBI","website_slug":"mobius","rank":266,"circulating_supply":376657502,"total_supply":887990859,"max_supply":null,"quotes":{"USD":{"price":0.0616303,"volume_24h":174024,"market_cap":23213515,"percent_change_1h":-0.52,"percent_change_24h":-2.75,"percent_change_7d":24.67}},"last_updated":1532328282},"1779":{"id":1779,"name":"Wagerr","symbol":"WGR","website_slug":"wagerr","rank":267,"circulating_supply":183000000,"total_supply":198360471,"max_supply":null,"quotes":{"USD":{"price":0.126683,"volume_24h":32476.1,"market_cap":23182989,"percent_change_1h":0.18,"percent_change_24h":-0.88,"percent_change_7d":3.49}},"last_updated":1532328275},"132":{"id":132,"name":"Counterparty","symbol":"XCP","website_slug":"counterparty","rank":268,"circulating_supply":2616137,"total_supply":2616137,"max_supply":null,"quotes":{"USD":{"price":8.80319,"volume_24h":59396.4,"market_cap":23030348,"percent_change_1h":-0.64,"percent_change_24h":6.12,"percent_change_7d":16.71}},"last_updated":1532328265},"2380":{"id":2380,"name":"ATN","symbol":"ATN","website_slug":"atn","rank":269,"circulating_supply":84302524,"total_supply":210000000,"max_supply":null,"quotes":{"USD":{"price":0.271731,"volume_24h":515358,"market_cap":22907609,"percent_change_1h":-0.05,"percent_change_24h":3.45,"percent_change_7d":5.02}},"last_updated":1532328280},"2841":{"id":2841,"name":"LoyalCoin","symbol":"LYL","website_slug":"loyalcoin","rank":270,"circulating_supply":4934048956,"total_supply":9000000000,"max_supply":null,"quotes":{"USD":{"price":0.00463456,"volume_24h":34589.2,"market_cap":22867146,"percent_change_1h":-3.19,"percent_change_24h":7.06,"percent_change_7d":3.4}},"last_updated":1532328288},"2698":{"id":2698,"name":"Hydro","symbol":"HYDRO","website_slug":"hydrogen","rank":271,"circulating_supply":3090523039,"total_supply":11111111111,"max_supply":null,"quotes":{"USD":{"price":0.00738869,"volume_24h":408757,"market_cap":22834917,"percent_change_1h":0.18,"percent_change_24h":-4.13,"percent_change_7d":-9.66}},"last_updated":1532328286},"2430":{"id":2430,"name":"Hydro Protocol","symbol":"HOT","website_slug":"hydro-protocol","rank":272,"circulating_supply":702000000,"total_supply":1560000000,"max_supply":null,"quotes":{"USD":{"price":0.0324378,"volume_24h":383651,"market_cap":22771336,"percent_change_1h":1.03,"percent_change_24h":12.56,"percent_change_7d":9.52}},"last_updated":1532328283},"2633":{"id":2633,"name":"Stakenet","symbol":"XSN","website_slug":"stakenet","rank":273,"circulating_supply":70454442,"total_supply":80146884,"max_supply":null,"quotes":{"USD":{"price":0.322985,"volume_24h":98903.1,"market_cap":22755728,"percent_change_1h":-0.03,"percent_change_24h":-2.94,"percent_change_7d":-10.35}},"last_updated":1532328284},"2876":{"id":2876,"name":"Ternio","symbol":"TERN","website_slug":"ternio","rank":274,"circulating_supply":407390714,"total_supply":999953473,"max_supply":null,"quotes":{"USD":{"price":0.0551207,"volume_24h":2067040,"market_cap":22455661,"percent_change_1h":-0.12,"percent_change_24h":-1.76,"percent_change_7d":-5.5}},"last_updated":1532328286},"1856":{"id":1856,"name":"district0x","symbol":"DNT","website_slug":"district0x","rank":275,"circulating_supply":600000000,"total_supply":1000000000,"max_supply":null,"quotes":{"USD":{"price":0.0373937,"volume_24h":349400,"market_cap":22436220,"percent_change_1h":0.24,"percent_change_24h":1.94,"percent_change_7d":5.41}},"last_updated":1532328275},"2612":{"id":2612,"name":"BitRent","symbol":"RNTB","website_slug":"bitrent","rank":276,"circulating_supply":841750000,"total_supply":942000000,"max_supply":null,"quotes":{"USD":{"price":0.0264706,"volume_24h":561560,"market_cap":22281628,"percent_change_1h":0.25,"percent_change_24h":6.27,"percent_change_7d":14.82}},"last_updated":1532328286},"1409":{"id":1409,"name":"SingularDTV","symbol":"SNGLS","website_slug":"singulardtv","rank":277,"circulating_supply":600000000,"total_supply":1000000000,"max_supply":null,"quotes":{"USD":{"price":0.03687,"volume_24h":236179,"market_cap":22122000,"percent_change_1h":0.19,"percent_change_24h":0.79,"percent_change_7d":1.94}},"last_updated":1532328274},"2341":{"id":2341,"name":"SwftCoin","symbol":"SWFTC","website_slug":"swftcoin","rank":278,"circulating_supply":3639990384,"total_supply":10000000000,"max_supply":null,"quotes":{"USD":{"price":0.00606885,"volume_24h":5170730,"market_cap":22090556,"percent_change_1h":0.55,"percent_change_24h":-0.69,"percent_change_7d":-0.94}},"last_updated":1532328278},"2780":{"id":2780,"name":"NKN","symbol":"NKN","website_slug":"nkn","rank":279,"circulating_supply":146347359,"total_supply":700000000,"max_supply":1000000000,"quotes":{"USD":{"price":0.150554,"volume_24h":883819,"market_cap":22033180,"percent_change_1h":2.42,"percent_change_24h":3.31,"percent_change_7d":-14}},"last_updated":1532328287},"1281":{"id":1281,"name":"ION","symbol":"ION","website_slug":"ion","rank":280,"circulating_supply":21692425,"total_supply":27592425,"max_supply":null,"quotes":{"USD":{"price":1.01019,"volume_24h":9851.33,"market_cap":21913471,"percent_change_1h":-0.23,"percent_change_24h":1.14,"percent_change_7d":-2.7}},"last_updated":1532328271},"2058":{"id":2058,"name":"AirSwap","symbol":"AST","website_slug":"airswap","rank":281,"circulating_supply":150000000,"total_supply":500000000,"max_supply":null,"quotes":{"USD":{"price":0.145635,"volume_24h":660022,"market_cap":21845250,"percent_change_1h":-0.03,"percent_change_24h":-0.17,"percent_change_7d":1}},"last_updated":1532328278},"2096":{"id":2096,"name":"Ripio Credit Network","symbol":"RCN","website_slug":"ripio-credit-network","rank":282,"circulating_supply":491580791,"total_supply":999942647,"max_supply":null,"quotes":{"USD":{"price":0.043732,"volume_24h":1428770,"market_cap":21497811,"percent_change_1h":-0.77,"percent_change_24h":3.67,"percent_change_7d":1.93}},"last_updated":1532328279},"1715":{"id":1715,"name":"MobileGo","symbol":"MGO","website_slug":"mobilego","rank":283,"circulating_supply":98028877,"total_supply":100000000,"max_supply":null,"quotes":{"USD":{"price":0.218051,"volume_24h":363511,"market_cap":21375295,"percent_change_1h":-0.14,"percent_change_24h":-2.67,"percent_change_7d":4.31}},"last_updated":1532328272},"2577":{"id":2577,"name":"Ravencoin","symbol":"RVN","website_slug":"ravencoin","rank":284,"circulating_supply":1230815206,"total_supply":1230815206,"max_supply":21000000000,"quotes":{"USD":{"price":0.0173346,"volume_24h":248880,"market_cap":21335689,"percent_change_1h":-0.96,"percent_change_24h":5.33,"percent_change_7d":25.02}},"last_updated":1532328285},"2481":{"id":2481,"name":"Zeepin","symbol":"ZPT","website_slug":"zeepin","rank":285,"circulating_supply":500000000,"total_supply":1000000000,"max_supply":null,"quotes":{"USD":{"price":0.0425035,"volume_24h":213865,"market_cap":21251750,"percent_change_1h":-0.46,"percent_change_24h":7.51,"percent_change_7d":27.4}},"last_updated":1532328280},"2219":{"id":2219,"name":"SpankChain","symbol":"SPANK","website_slug":"spankchain","rank":286,"circulating_supply":300043386,"total_supply":1000000000,"max_supply":null,"quotes":{"USD":{"price":0.0707112,"volume_24h":265200,"market_cap":21216428,"percent_change_1h":-0.53,"percent_change_24h":0.68,"percent_change_7d":2.33}},"last_updated":1532328278},"1298":{"id":1298,"name":"LBRY Credits","symbol":"LBC","website_slug":"library-credit","rank":287,"circulating_supply":167241196,"total_supply":542141200,"max_supply":null,"quotes":{"USD":{"price":0.126527,"volume_24h":122823,"market_cap":21160527,"percent_change_1h":-0.56,"percent_change_24h":5.73,"percent_change_7d":20.06}},"last_updated":1532328267},"2540":{"id":2540,"name":"Litecoin Cash","symbol":"LCC","website_slug":"litecoin-cash","rank":288,"circulating_supply":579118207,"total_supply":579118207,"max_supply":840000000,"quotes":{"USD":{"price":0.0357167,"volume_24h":108687,"market_cap":20684191,"percent_change_1h":-2.36,"percent_change_24h":3.2,"percent_change_7d":-12.63}},"last_updated":1532328282},"1847":{"id":1847,"name":"Mothership","symbol":"MSP","website_slug":"mothership","rank":289,"circulating_supply":140000000,"total_supply":200000000,"max_supply":null,"quotes":{"USD":{"price":0.147319,"volume_24h":88167.7,"market_cap":20624660,"percent_change_1h":0,"percent_change_24h":2.78,"percent_change_7d":10.93}},"last_updated":1532328274},"362":{"id":362,"name":"CloakCoin","symbol":"CLOAK","website_slug":"cloakcoin","rank":290,"circulating_supply":5166339,"total_supply":5166339,"max_supply":null,"quotes":{"USD":{"price":3.98071,"volume_24h":325026,"market_cap":20565697,"percent_change_1h":-0.83,"percent_change_24h":0.66,"percent_change_7d":10.17}},"last_updated":1532328268},"224":{"id":224,"name":"FairCoin","symbol":"FAIR","website_slug":"faircoin","rank":291,"circulating_supply":53193831,"total_supply":53193831,"max_supply":null,"quotes":{"USD":{"price":0.385834,"volume_24h":1687.9,"market_cap":20523989,"percent_change_1h":0.17,"percent_change_24h":2.58,"percent_change_7d":17.29}},"last_updated":1532328264},"1660":{"id":1660,"name":"TokenCard","symbol":"TKN","website_slug":"tokencard","rank":292,"circulating_supply":24166670,"total_supply":39406760,"max_supply":null,"quotes":{"USD":{"price":0.848636,"volume_24h":130479,"market_cap":20508707,"percent_change_1h":0.14,"percent_change_24h":1.08,"percent_change_7d":-15}},"last_updated":1532328272},"1500":{"id":1500,"name":"Wings","symbol":"WINGS","website_slug":"wings","rank":293,"circulating_supply":89708333,"total_supply":100000000,"max_supply":null,"quotes":{"USD":{"price":0.227912,"volume_24h":1276340,"market_cap":20445606,"percent_change_1h":-0.01,"percent_change_24h":-0.76,"percent_change_7d":12.83}},"last_updated":1532328272},"2641":{"id":2641,"name":"Apex","symbol":"CPX","website_slug":"apex","rank":294,"circulating_supply":432838449,"total_supply":676989090,"max_supply":null,"quotes":{"USD":{"price":0.0470001,"volume_24h":250531,"market_cap":20343450,"percent_change_1h":0.1,"percent_change_24h":-13.46,"percent_change_7d":-22.48}},"last_updated":1532328287},"2342":{"id":2342,"name":"Covesting","symbol":"COV","website_slug":"covesting","rank":295,"circulating_supply":17500000,"total_supply":20000000,"max_supply":null,"quotes":{"USD":{"price":1.16212,"volume_24h":62413.8,"market_cap":20337100,"percent_change_1h":0.42,"percent_change_24h":2.57,"percent_change_7d":0.74}},"last_updated":1532328282},"2766":{"id":2766,"name":"Cryptaur","symbol":"CPT","website_slug":"cryptaur","rank":296,"circulating_supply":6797851516,"total_supply":27662180148,"max_supply":null,"quotes":{"USD":{"price":0.00297321,"volume_24h":78507.6,"market_cap":20211440,"percent_change_1h":-2.63,"percent_change_24h":-2.8,"percent_change_7d":-1.62}},"last_updated":1532328289},"2006":{"id":2006,"name":"Cobinhood","symbol":"COB","website_slug":"cobinhood","rank":297,"circulating_supply":367697387,"total_supply":1000000000,"max_supply":null,"quotes":{"USD":{"price":0.0546372,"volume_24h":27442.7,"market_cap":20089956,"percent_change_1h":5.64,"percent_change_24h":3.53,"percent_change_7d":-2}},"last_updated":1532328272},"2320":{"id":2320,"name":"UTRUST","symbol":"UTK","website_slug":"utrust","rank":298,"circulating_supply":311262670,"total_supply":500000000,"max_supply":null,"quotes":{"USD":{"price":0.064361,"volume_24h":321027,"market_cap":20033177,"percent_change_1h":0.3,"percent_change_24h":-10.94,"percent_change_7d":-13.34}},"last_updated":1532328285},"2318":{"id":2318,"name":"Neumark","symbol":"NEU","website_slug":"neumark","rank":299,"circulating_supply":28731068,"total_supply":53005272,"max_supply":1500000000,"quotes":{"USD":{"price":0.690127,"volume_24h":121282,"market_cap":19828086,"percent_change_1h":2.09,"percent_change_24h":38.12,"percent_change_7d":80.28}},"last_updated":1532328281}},"metadata":{"timestamp":1532327880,"num_cryptocurrencies":1656,"error":null}}}