{"data":{"0":null,"symbol":["BZ","BZ","BZ","BZ","BZ","BZ","BZ","BZ"],"history":{"2":{"position":1379,"name":"Bit-Z Token","symbol":"BZ","identifier":"bit-z-token","category":"currency","marketCap":{"usd":null,"btc":0,"eur":0,"cny":0,"gbp":0,"cad":0,"rub":0,"hkd":0,"jpy":0,"aud":0},"price":{"usd":0.195561,"btc":0,"eur":0,"cny":0,"cad":0,"rub":0,"hkd":0,"jpy":0,"aud":0},"availableSupply":null,"volume24":{"usd":7425580,"btc":0,"eur":0,"cny":0,"gbp":0,"cad":0,"rub":0,"hkd":0,"jpy":0,"aud":0},"change1h":-0.62,"change24h":-3.11,"change7d":null,"timestamp":1531624664,"date":"14-07-2018"},"3":{"position":1383,"name":"Bit-Z Token","symbol":"BZ","identifier":"bit-z-token","category":"currency","marketCap":{"usd":null,"btc":0,"eur":0,"cny":0,"gbp":0,"cad":0,"rub":0,"hkd":0,"jpy":0,"aud":0},"price":{"usd":0.239267,"btc":0,"eur":0,"cny":0,"cad":0,"rub":0,"hkd":0,"jpy":0,"aud":0},"availableSupply":null,"volume24":{"usd":10737200,"btc":0,"eur":0,"cny":0,"gbp":0,"cad":0,"rub":0,"hkd":0,"jpy":0,"aud":0},"change1h":-0.24,"change24h":0.02,"change7d":null,"timestamp":1531797414,"date":"16-07-2018"},"4":{"position":1385,"name":"Bit-Z Token","symbol":"BZ","identifier":"bit-z-token","category":"currency","marketCap":{"usd":null,"btc":0,"eur":0,"cny":0,"gbp":0,"cad":0,"rub":0,"hkd":0,"jpy":0,"aud":0},"price":{"usd":0.238574,"btc":0,"eur":0,"cny":0,"cad":0,"rub":0,"hkd":0,"jpy":0,"aud":0},"availableSupply":null,"volume24":{"usd":8031280,"btc":0,"eur":0,"cny":0,"gbp":0,"cad":0,"rub":0,"hkd":0,"jpy":0,"aud":0},"change1h":-1.65,"change24h":-0.78,"change7d":-18.32,"timestamp":1531883448,"date":"17-07-2018"},"5":{"position":1383,"name":"Bit-Z Token","symbol":"BZ","identifier":"bit-z-token","category":"currency","marketCap":{"usd":null,"btc":0,"eur":0,"cny":0,"gbp":0,"cad":0,"rub":0,"hkd":0,"jpy":0,"aud":0},"price":{"usd":0.245261,"btc":0,"eur":0,"cny":0,"cad":0,"rub":0,"hkd":0,"jpy":0,"aud":0},"availableSupply":null,"volume24":{"usd":12114400,"btc":0,"eur":0,"cny":0,"gbp":0,"cad":0,"rub":0,"hkd":0,"jpy":0,"aud":0},"change1h":0.33,"change24h":1.18,"change7d":13.95,"timestamp":1531969847,"date":"18-07-2018"},"6":{"position":1386,"name":"Bit-Z Token","symbol":"BZ","identifier":"bit-z-token","category":"currency","marketCap":{"usd":null,"btc":0,"eur":0,"cny":0,"gbp":0,"cad":0,"rub":0,"hkd":0,"jpy":0,"aud":0},"price":{"usd":0.254477,"btc":0,"eur":0,"cny":0,"cad":0,"rub":0,"hkd":0,"jpy":0,"aud":0},"availableSupply":null,"volume24":{"usd":16768600,"btc":0,"eur":0,"cny":0,"gbp":0,"cad":0,"rub":0,"hkd":0,"jpy":0,"aud":0},"change1h":-1.01,"change24h":3.7,"change7d":16.25,"timestamp":1532056245,"date":"19-07-2018"},"7":{"position":1386,"name":"Bit-Z Token","symbol":"BZ","identifier":"bit-z-token","category":"currency","marketCap":{"usd":null,"btc":0,"eur":0,"cny":0,"gbp":0,"cad":0,"rub":0,"hkd":0,"jpy":0,"aud":0},"price":{"usd":0.23846,"btc":0,"eur":0,"cny":0,"cad":0,"rub":0,"hkd":0,"jpy":0,"aud":0},"availableSupply":null,"volume24":{"usd":9268030,"btc":0,"eur":0,"cny":0,"gbp":0,"cad":0,"rub":0,"hkd":0,"jpy":0,"aud":0},"change1h":-1.37,"change24h":-6.27,"change7d":19.56,"timestamp":1532142647,"date":"20-07-2018"},"8":{"position":1385,"name":"Bit-Z Token","symbol":"BZ","identifier":"bit-z-token","category":"currency","marketCap":{"usd":null,"btc":0,"eur":0,"cny":0,"gbp":0,"cad":0,"rub":0,"hkd":0,"jpy":0,"aud":0},"price":{"usd":0.23693,"btc":0,"eur":0,"cny":0,"cad":0,"rub":0,"hkd":0,"jpy":0,"aud":0},"availableSupply":null,"volume24":{"usd":11899300,"btc":0,"eur":0,"cny":0,"gbp":0,"cad":0,"rub":0,"hkd":0,"jpy":0,"aud":0},"change1h":0.55,"change24h":-0.91,"change7d":18.67,"timestamp":1532229072,"date":"21-07-2018"},"9":{"position":1390,"name":"Bit-Z Token","symbol":"BZ","identifier":"bit-z-token","category":"currency","marketCap":{"usd":null,"btc":0,"eur":0,"cny":0,"gbp":0,"cad":0,"rub":0,"hkd":0,"jpy":0,"aud":0},"price":{"usd":0.234214,"btc":0,"eur":0,"cny":0,"cad":0,"rub":0,"hkd":0,"jpy":0,"aud":0},"availableSupply":null,"volume24":{"usd":13644100,"btc":0,"eur":0,"cny":0,"gbp":0,"cad":0,"rub":0,"hkd":0,"jpy":0,"aud":0},"change1h":1.66,"change24h":-0.77,"change7d":0.68,"timestamp":1532315446,"date":"22-07-2018"}},"s":{"price":{"gbp":[0,0,0,0,0,0,0,0]}}}}